{"response": {"status": {"code": 0, "message": "Success", "version": "4.2"}, "songs": [{"song_hotttnesss": 0.449065, "song_currency_rank": 9103, "artist_discovery_rank": 4143, "title": "Alleyways", "artist_discovery": 0.537828246471514, "song_hotttnesss_rank": 12848, "artist_name": "The Neighbourhood", "song_type": ["studio", "electric"], "artist_hotttnesss": 0.757863, "artist_familiarity_rank": 2946, "artist_location": {"latitude": 34.032383, "location": "Newbury Park, CA", "longitude": -119.1343}, "song_currency": 0.061323585574772216, "id": "SORRJDK13ED28B3EB4", "artist_familiarity": 0.604337, "artist_id": "ARRFDAA12472CE3191", "artist_hotttnesss_rank": 721, "audio_summary": {"time_signature": 4, "analysis_url": "http://echonest-analysis.s3.amazonaws.com/TR/hyAQag-9PSZuiXzCDOkqg5-svCnDo59aMKJPdobM_5Q25TwTI3gpbkr185Gxcm-rUr9133qaus-8E6J6s%3D/3/full.json?AWSAccessKeyId=AKIAJRDFEY23UEVW42BQ&Expires=1445733548&Signature=fzSwkgByKA/A3Z1UKpDyg41yRGU%3D", "energy": 0.830893, "liveness": 0.118544, "tempo": 101.03, "speechiness": 0.027287, "acousticness": 0.001021, "danceability": 0.622163, "instrumentalness": 0.802896, "key": 5, "duration": 267.85333, "loudness": -4.819, "audio_md5": "", "valence": 0.362832, "mode": 0}}, {"song_hotttnesss": 0.449065, "song_currency_rank": 9103, "artist_discovery_rank": 4143, "title": "Alleyways", "artist_discovery": 0.537828246471514, "song_hotttnesss_rank": 12848, "artist_name": "The Neighbourhood", "song_type": ["studio", "electric"], "artist_hotttnesss": 0.757863, "artist_familiarity_rank": 2946, "artist_location": {"latitude": 34.032383, "location": "Newbury Park, CA", "longitude": -119.1343}, "song_currency": 0.061323585574772216, "id": "SOCEJRI13E906FED56", "artist_familiarity": 0.604337, "artist_id": "ARRFDAA12472CE3191", "artist_hotttnesss_rank": 721, "audio_summary": {"time_signature": 4, "analysis_url": "http://echonest-analysis.s3.amazonaws.com/TR/dTUDVwVgkeshcBgOmBatCunUCK6w%3D%3D/3/full.json?AWSAccessKeyId=AKIAJRDFEY23UEVW42BQ&Expires=1445733548&Signature=b0OvwX3NWYYA0YKOOIU5TSMBrXY%3D", "energy": 0.819001, "liveness": 0.294066, "tempo": 101.048, "speechiness": 0.029431, "acousticness": 0.001156, "danceability": 0.621209, "instrumentalness": 0.748425, "key": 8, "duration": 253.51156, "loudness": -4.278, "audio_md5": "5bac3af3ea22894e21403fbac233cfc5", "valence": 0.414885, "mode": 1}}]}}