{"response": {"status": {"code": 0, "message": "Success", "version": "4.2"}, "songs": [{"song_hotttnesss": 0.477898, "song_currency_rank": 24545, "artist_discovery_rank": 6017, "title": "Philosophize In It! Chemicalize With It!", "artist_discovery": 0.5235890788690302, "song_hotttnesss_rank": 7583, "artist_name": "Kishi Bashi", "song_type": ["studio", "electric", "vocal"], "artist_hotttnesss": 0.642152, "artist_familiarity_rank": 9169, "artist_location": {"latitude": 47.6036, "location": "Seattle, WA, US", "longitude": -122.329}, "song_currency": 0.02919213104715248, "id": "SOSAXKC144DFE5577A", "artist_familiarity": 0.514365, "artist_id": "ARNEMUD1312083EB67", "artist_hotttnesss_rank": 2942, "audio_summary": {"time_signature": 4, "analysis_url": "http://echonest-analysis.s3.amazonaws.com/TR/eDMLSwp6yR_sa-Mlw_r3WfUkborQLc527eSyhSiXrXumQCBBIt7UNXaeUZLfX6rzCRqTBQfZUmloxOd7M%3D/3/full.json?AWSAccessKeyId=AKIAJRDFEY23UEVW42BQ&Expires=1445730418&Signature=nwjje8yG2pQDCRJw2DOX5Cknq5I%3D", "energy": 0.828411, "liveness": 0.157977, "tempo": 136.899, "speechiness": 0.037639, "acousticness": 0.245096, "danceability": 0.316218, "instrumentalness": 0.000356, "key": 0, "duration": 200.53333, "loudness": -5.313, "audio_md5": "", "valence": 0.328404, "mode": 1}}, {"song_hotttnesss": 0.0, "song_currency_rank": 797204, "artist_discovery_rank": 6017, "title": "Philosophize In It! Chemicalize With It! (Tokyo Mix) [Bonus Track]", "artist_discovery": 0.5235890788690302, "artist_name": "Kishi Bashi", "song_type": ["remix", "studio", "electric", "vocal"], "artist_hotttnesss": 0.642152, "artist_familiarity_rank": 9169, "artist_location": {"latitude": 47.6036, "location": "Seattle, WA, US", "longitude": -122.329}, "song_currency": 0.0007208008898776417, "id": "SOUYNWP1423EC1C513", "artist_familiarity": 0.514365, "artist_id": "ARNEMUD1312083EB67", "artist_hotttnesss_rank": 2942, "audio_summary": {"time_signature": 4, "analysis_url": "http://echonest-analysis.s3.amazonaws.com/TR/iVl05wg2TS9bvqCrh6Yuq-Wj6VIgVcUHBrEoUmnm_wh7S3GlnmWpTCKVOEe7ZmTgLdq9UThwXK0CJFBS0%3D/3/full.json?AWSAccessKeyId=AKIAJRDFEY23UEVW42BQ&Expires=1445730418&Signature=rk%2Bo6gNIQmLVqecpodmeZQsw5tk%3D", "energy": 0.79157, "liveness": 0.386903, "tempo": 135.198, "speechiness": 0.09175, "acousticness": 0.256508, "danceability": 0.514886, "instrumentalness": 1e-06, "key": 0, "duration": 210.58621, "loudness": -5.937, "audio_md5": "f82e790c5e91a30ec070484bb695f3db", "valence": 0.260907, "mode": 1}}]}}