{"response": {"status": {"code": 0, "message": "Success", "version": "4.2"}, "songs": [{"song_hotttnesss": 0.0, "title": "Whatever We Want (Clean)", "artist_discovery": 0.4484506236253061, "artist_name": "Chiddy Bang", "song_type": ["studio", "electric", "vocal"], "artist_hotttnesss": 0.601563, "artist_location": {"latitude": 40.001811, "location": "Philadelphia, PA", "longitude": -75.11787}, "song_currency": 0.0, "artist_familiarity": 0.573651, "artist_id": "ARPZMNJ122BCFC9A42", "id": "SOSHMDW1372F3EF33A", "audio_summary": {"time_signature": 4, "analysis_url": "http://echonest-analysis.s3.amazonaws.com/TR/WksxHwPs1Uqyo_fz-_51o39_y560HQFGh0KyO6/3/full.json?AWSAccessKeyId=AKIAJRDFEY23UEVW42BQ&Expires=1445728465&Signature=N8Pn3nmt%2BCvccbgKTz4K24Hb/So%3D", "energy": 0.624929, "liveness": 0.129401, "tempo": 98.585, "speechiness": 0.274048, "acousticness": 0.000563, "danceability": 0.576575, "instrumentalness": 1e-06, "key": 10, "duration": 183.87882, "loudness": -7.259, "audio_md5": "f3a421dc829d99bd6070d01b6a93b0dd", "valence": 0.53152, "mode": 0}}, {"song_hotttnesss": 0.256112, "song_currency_rank": 318071, "artist_discovery_rank": 50765, "title": "Whatever We Want", "artist_discovery": 0.4484506236253061, "song_hotttnesss_rank": 282302, "artist_name": "Chiddy Bang", "song_type": ["studio", "electric", "vocal"], "artist_hotttnesss": 0.601563, "artist_familiarity_rank": 4413, "artist_location": {"latitude": 40.001811, "location": "Philadelphia, PA", "longitude": -75.11787}, "song_currency": 0.0015953372189841798, "id": "SOVITES1372F3EF9D1", "artist_familiarity": 0.573651, "artist_id": "ARPZMNJ122BCFC9A42", "artist_hotttnesss_rank": 5400, "audio_summary": {"time_signature": 4, "analysis_url": "http://echonest-analysis.s3.amazonaws.com/TR/u3ZTOAkisgzyC-p_1u3vbejKCCzBysXttuad-WrzXiCHQxDWDHQCAN-kNr0xr6ex3q58kctZWesQo4r6M%3D/3/full.json?AWSAccessKeyId=AKIAJRDFEY23UEVW42BQ&Expires=1445728465&Signature=sy6qAXDeMDt4GfudLPQl4IuKO9s%3D", "energy": 0.661825, "liveness": 0.123037, "tempo": 99.932, "speechiness": 0.285299, "acousticness": 0.001815, "danceability": 0.578533, "instrumentalness": 1e-06, "key": 10, "duration": 184.13333, "loudness": -6.536, "audio_md5": "", "valence": 0.50038, "mode": 0}}]}}