{"response": {"status": {"code": 0, "message": "Success", "version": "4.2"}, "songs": [{"song_hotttnesss": 0.077436, "song_currency_rank": 4909928, "artist_discovery_rank": 97325, "title": "Losing My Amarok", "artist_discovery": 0.4134906711811825, "song_hotttnesss_rank": 2428135, "artist_name": "The White Panda", "song_type": ["studio", "electric", "vocal"], "artist_hotttnesss": 0.493656, "artist_familiarity_rank": 11580, "artist_location": {"latitude": 37.3831, "location": "Los Altos, CA, US", "longitude": -122.114}, "song_currency": 6.000000000000001e-05, "id": "SOBIBWU14525EED3EE", "artist_familiarity": 0.495797, "artist_id": "AREJHRG12F7935451A", "artist_hotttnesss_rank": 41522, "audio_summary": {"time_signature": 4, "analysis_url": "http://echonest-analysis.s3.amazonaws.com/TR/QVIBlw4c0R4_vvGNeI8BHFUT6Upsz79tRH_ornEexAzDMnmnjXriYWUm3ytMClIDPc7vI9GHEL7SN3_GI%3D/3/full.json?AWSAccessKeyId=AKIAJRDFEY23UEVW42BQ&Expires=1445741051&Signature=mT5KkCy5K3lURGP4svHsmoXbzW8%3D", "energy": 0.974339, "liveness": 0.265506, "tempo": 126.26, "speechiness": 0.073136, "acousticness": 0.01355, "danceability": 0.535918, "instrumentalness": 2.5e-05, "key": 5, "duration": 108.3907, "loudness": -4.168, "audio_md5": "34132b9969fd57b00df94047a8ec44b7", "valence": 0.364843, "mode": 1}}]}}