{"response": {"status": {"code": 0, "message": "Success", "version": "4.2"}, "songs": [{"song_hotttnesss": 0.444599, "song_currency_rank": 10696, "artist_discovery_rank": 301730, "title": "Safe From Harm", "artist_discovery": 0.33540932713039817, "song_hotttnesss_rank": 13928, "artist_name": "Massive Attack", "song_type": ["studio", "electric", "vocal"], "artist_hotttnesss": 0.709756, "artist_familiarity_rank": 120, "artist_location": {"latitude": 51.4537, "location": "Bristol, England, GB", "longitude": -2.59156}, "song_currency": 0.05693486173738252, "id": "SOAZFDX13E904AFB8A", "artist_familiarity": 0.799857, "artist_id": "ARNF13I1187FB562A5", "artist_hotttnesss_rank": 1413, "audio_summary": {"time_signature": 4, "analysis_url": "http://echonest-analysis.s3.amazonaws.com/TR/i4TGQAvbdHTt1nS4_gdoJpd_6VVXDAoeJHSgm9/3/full.json?AWSAccessKeyId=AKIAJRDFEY23UEVW42BQ&Expires=1445734305&Signature=1wrZNOcj3ZXx0BAybvL5L7T2lro%3D", "energy": 0.549906, "liveness": 0.236751, "tempo": 81.526, "speechiness": 0.071351, "acousticness": 0.021675, "danceability": 0.647997, "instrumentalness": 0.00092, "key": 4, "duration": 297.91955, "loudness": -18.228, "audio_md5": "76eba34abc7ec7c0e01737b0c500d86a", "valence": 0.866493, "mode": 1}}, {"song_hotttnesss": 0.444599, "song_currency_rank": 10696, "artist_discovery_rank": 301730, "title": "Safe From Harm", "artist_discovery": 0.33540932713039817, "song_hotttnesss_rank": 13928, "artist_name": "Massive Attack", "song_type": ["studio", "electric", "vocal"], "artist_hotttnesss": 0.709756, "artist_familiarity_rank": 120, "artist_location": {"latitude": 51.4537, "location": "Bristol, England, GB", "longitude": -2.59156}, "song_currency": 0.05693486173738252, "id": "SOJMHBU1372A33C4EB", "artist_familiarity": 0.799857, "artist_id": "ARNF13I1187FB562A5", "artist_hotttnesss_rank": 1413, "audio_summary": {"time_signature": 4, "analysis_url": "http://echonest-analysis.s3.amazonaws.com/TR/MMzjZAf03A3mO3uUGpfYRWB-MfVcojQjvlDcXK3ezIL4Xa-zLT7rowtvBtBAnu2w_l--BVWZ2pU3hUgsg%3D/3/full.json?AWSAccessKeyId=AKIAJRDFEY23UEVW42BQ&Expires=1445734305&Signature=Oo17Z5Ky2lx1HLGzjUu5taMkrEQ%3D", "energy": 0.671913, "liveness": 0.097571, "tempo": 82.272, "speechiness": 0.041067, "acousticness": 0.065851, "danceability": 0.699861, "instrumentalness": 0.104163, "key": 9, "duration": 318.97333, "loudness": -12.195, "audio_md5": "", "valence": 0.915648, "mode": 1}}, {"song_hotttnesss": 0.0, "artist_discovery_rank": 301730, "title": "11. Safe From Harm", "artist_discovery": 0.33540932713039817, "artist_hotttnesss_rank": 1413, "artist_name": "Massive Attack", "song_type": ["live", "vocal"], "artist_hotttnesss": 0.709756, "artist_familiarity_rank": 120, "artist_location": {"latitude": 51.4537, "location": "Bristol, England, GB", "longitude": -2.59156}, "song_currency": 0.0, "artist_familiarity": 0.799857, "artist_id": "ARNF13I1187FB562A5", "id": "SOORXVE12B0B80BD7D", "audio_summary": {"time_signature": 4, "analysis_url": "http://echonest-analysis.s3.amazonaws.com/TR/TRRACHI123E85819F9/3/full.json?AWSAccessKeyId=AKIAJRDFEY23UEVW42BQ&Expires=1445734305&Signature=k2kdiUVDmJ20Xq5MCELD4xMAAbk%3D", "energy": 0.920774, "liveness": 0.912804, "tempo": 85.982, "speechiness": 0.038209, "acousticness": 0.698929, "danceability": 0.415931, "instrumentalness": 0.230405, "key": 4, "duration": 438.80444, "loudness": -9.797, "audio_md5": "6b9c620a9ad41712c5c7eb6a52071789", "valence": 0.289209, "mode": 0}}, {"song_hotttnesss": 0.153252, "song_currency_rank": 3772601, "artist_discovery_rank": 301730, "title": "Safe From Harm (7'' Version)", "artist_discovery": 0.33540932713039817, "song_hotttnesss_rank": 957959, "artist_name": "Massive Attack", "song_type": ["remix", "studio", "electric", "vocal"], "artist_hotttnesss": 0.709756, "artist_familiarity_rank": 120, "artist_location": {"latitude": 51.4537, "location": "Bristol, England, GB", "longitude": -2.59156}, "song_currency": 0.00015527950310559007, "id": "SOFRQUL12A8C141395", "artist_familiarity": 0.799857, "artist_id": "ARNF13I1187FB562A5", "artist_hotttnesss_rank": 1413, "audio_summary": {"time_signature": 4, "analysis_url": "http://echonest-analysis.s3.amazonaws.com/TR/8AD5-wzhGU3D38RomFx52BOG2Env406fGoN4309rQ4lyi4-R0Fbblz1FM77PzUqO63v1rfMRcfGr68lFA%3D/3/full.json?AWSAccessKeyId=AKIAJRDFEY23UEVW42BQ&Expires=1445734305&Signature=E7kWDj883TzVSHiZpJ3vUAAEl0A%3D", "energy": 0.830056, "liveness": 0.137841, "tempo": 163.131, "speechiness": 0.072784, "acousticness": 0.026275, "danceability": 0.642552, "instrumentalness": 0.001991, "key": 6, "duration": 268.36, "loudness": -8.08, "audio_md5": "", "valence": 0.8831, "mode": 0}}, {"song_hotttnesss": 0.14716, "song_currency_rank": 3889850, "artist_discovery_rank": 301730, "title": "Safe From Harm (12'' Version)", "artist_discovery": 0.33540932713039817, "song_hotttnesss_rank": 1023816, "artist_name": "Massive Attack", "song_type": ["remix", "studio", "electric", "vocal"], "artist_hotttnesss": 0.709756, "artist_familiarity_rank": 120, "artist_location": {"latitude": 51.4537, "location": "Bristol, England, GB", "longitude": -2.59156}, "song_currency": 0.00013636363636363634, "id": "SOVTEFK1373EF45EB1", "artist_familiarity": 0.799857, "artist_id": "ARNF13I1187FB562A5", "artist_hotttnesss_rank": 1413, "audio_summary": {"time_signature": 4, "analysis_url": "http://echonest-analysis.s3.amazonaws.com/TR/gF8-PACxtE1NegDaH5-PzUmArWHJUlI0Y1laSP9S54BpReVDqnJMJ2U0vsjHBfZvky0aH_q-YcSxKasiE%3D/3/full.json?AWSAccessKeyId=AKIAJRDFEY23UEVW42BQ&Expires=1445734305&Signature=iZukU3EyrZ65ufXDprlwI8nB/SU%3D", "energy": 0.807272, "liveness": 0.069524, "tempo": 163.441, "speechiness": 0.049228, "acousticness": 0.040377, "danceability": 0.671392, "instrumentalness": 0.372787, "key": 6, "duration": 417.37288, "loudness": -9.478, "audio_md5": "2fb33653386babd8cc87b3ecb900faa6", "valence": 0.918648, "mode": 0}}, {"song_hotttnesss": 0.252528, "song_currency_rank": 369822, "artist_discovery_rank": 301730, "title": "Safe From Harm (Perfecto Mix)", "artist_discovery": 0.33540932713039817, "song_hotttnesss_rank": 295413, "artist_name": "Massive Attack", "song_type": ["remix", "studio", "electric"], "artist_hotttnesss": 0.709756, "artist_familiarity_rank": 120, "artist_location": {"latitude": 51.4537, "location": "Bristol, England, GB", "longitude": -2.59156}, "song_currency": 0.0013885516045099742, "id": "SOHFVZJ13730AD6FBF", "artist_familiarity": 0.799857, "artist_id": "ARNF13I1187FB562A5", "artist_hotttnesss_rank": 1413, "audio_summary": {"time_signature": 4, "analysis_url": "http://echonest-analysis.s3.amazonaws.com/TR/3eGZygGdinGxO4Zr06ic7haOulZ9QepqHpDWvB8KiIB9psW8djI9A2KstvLQ7aubB2H1dX77bafks1bqo%3D/3/full.json?AWSAccessKeyId=AKIAJRDFEY23UEVW42BQ&Expires=1445734305&Signature=FPhS3%2BievuXpe3zZReE9bAAncdc%3D", "energy": 0.858025, "liveness": 0.062126, "tempo": 163.759, "speechiness": 0.032002, "acousticness": 0.017327, "danceability": 0.582005, "instrumentalness": 0.46402, "key": 9, "duration": 491.50667, "loudness": -9.249, "audio_md5": "", "valence": 0.961385, "mode": 1}}, {"song_hotttnesss": 0.223465, "song_currency_rank": 932122, "artist_discovery_rank": 301730, "title": "Safe From Harm (Just A Groove Dub)", "artist_discovery": 0.33540932713039817, "song_hotttnesss_rank": 423216, "artist_name": "Massive Attack", "song_type": ["remix", "studio", "electric"], "artist_hotttnesss": 0.709756, "artist_familiarity_rank": 120, "artist_location": {"latitude": 51.4537, "location": "Bristol, England, GB", "longitude": -2.59156}, "song_currency": 0.0005350052246603971, "id": "SOJGWIC13167714FB5", "artist_familiarity": 0.799857, "artist_id": "ARNF13I1187FB562A5", "artist_hotttnesss_rank": 1413, "audio_summary": {"time_signature": 4, "analysis_url": "http://echonest-analysis.s3.amazonaws.com/TR/Dvi2xw8IbFOql6kPxTJRa-3El7Zg0Vd3PG6hoSaBRNoSTMPFLQeofLzFFXyHnEDI3_xIQlohYv0ijKl0I%3D/3/full.json?AWSAccessKeyId=AKIAJRDFEY23UEVW42BQ&Expires=1445734305&Signature=2fq0weLsODYUZwu3wvnexLKKahM%3D", "energy": 0.800362, "liveness": 0.062234, "tempo": 81.903, "speechiness": 0.055988, "acousticness": 0.102867, "danceability": 0.713034, "instrumentalness": 0.556118, "key": 6, "duration": 193.22667, "loudness": -11.457, "audio_md5": "", "valence": 0.914818, "mode": 0}}, {"song_hotttnesss": 0.27829, "song_currency_rank": 3840832, "artist_discovery_rank": 301730, "title": "Safe from Harm (2012 Mix/Master)", "artist_discovery": 0.33540932713039817, "song_hotttnesss_rank": 213734, "artist_name": "Massive Attack", "song_type": ["remix", "studio", "electric", "vocal"], "artist_hotttnesss": 0.709756, "artist_familiarity_rank": 120, "artist_location": {"latitude": 51.4537, "location": "Bristol, England, GB", "longitude": -2.59156}, "song_currency": 0.00014500141602945342, "id": "SOQRWHT13CF18A25B3", "artist_familiarity": 0.799857, "artist_id": "ARNF13I1187FB562A5", "artist_hotttnesss_rank": 1413, "audio_summary": {"time_signature": 4, "analysis_url": "http://echonest-analysis.s3.amazonaws.com/TR/BlIIugxUb08mZBugoSxWMd3T7FCYVg7dW5OCVpm931EhxBIfu_mDR44xG8H18ZwsXIcw1PNZQByCM0I4Y%3D/3/full.json?AWSAccessKeyId=AKIAJRDFEY23UEVW42BQ&Expires=1445734305&Signature=cHVGyoOkwkYtixdYzizgNalExzY%3D", "energy": 0.830046, "liveness": 0.076602, "tempo": 82.274, "speechiness": 0.046896, "acousticness": 0.04383, "danceability": 0.677097, "instrumentalness": 0.31222, "key": 6, "duration": 319.0, "loudness": -6.604, "audio_md5": "", "valence": 0.844014, "mode": 0}}]}}