{"response": {"status": {"code": 0, "message": "Success", "version": "4.2"}, "songs": [{"song_hotttnesss": 0.260599, "song_currency_rank": 280064, "artist_discovery_rank": 13767, "title": "CONTROL", "artist_discovery": 0.49461445908997903, "song_hotttnesss_rank": 266798, "artist_name": "Capsule", "song_type": ["studio", "electric"], "artist_hotttnesss": 0.610144, "artist_familiarity_rank": 8717, "artist_location": {"latitude": 36.5062, "location": "Kanazawa-shi, Ishikawa Prefecture, JP", "longitude": 136.687}, "song_currency": 0.0018866719872306465, "id": "SOAJQGZ14596FAFFFE", "artist_familiarity": 0.518323, "artist_id": "ARBQ8FB1187B9956E2", "artist_hotttnesss_rank": 4634, "audio_summary": {"time_signature": 4, "analysis_url": "http://echonest-analysis.s3.amazonaws.com/TR/GB6D2AX3aaHuF5NyMBvC_6o72grnjI3YanGthiHak3gx4weLsIAbFgQbdc5oy0Wrqf1ZrgK7VFUdPTFnI%3D/3/full.json?AWSAccessKeyId=AKIAJRDFEY23UEVW42BQ&Expires=1445727776&Signature=DJhIXx4/vp97X3PMCymoGsyxTSs%3D", "energy": 0.590989, "liveness": 0.103147, "tempo": 95.0, "speechiness": 0.052604, "acousticness": 0.004412, "danceability": 0.505226, "instrumentalness": 0.868459, "key": 10, "duration": 276.50621, "loudness": -6.308, "audio_md5": "7119db98c847f2563c681b7cecd61e30", "valence": 0.629482, "mode": 0}}, {"song_hotttnesss": 0.040883, "title": "Control", "artist_name": "444 Capsule", "song_type": ["studio", "electric", "vocal"], "artist_hotttnesss": 0.0, "artist_location": {}, "song_currency": 2.173913043478261e-05, "artist_familiarity": 0.057325, "artist_id": "ARCIYTR149B8A79AA9", "id": "SOUJLZH149CB29C9F7", "audio_summary": {"time_signature": 4, "analysis_url": "http://echonest-analysis.s3.amazonaws.com/TR/z_ZM3gojTvDvr7vMAy0DVD21G7-qVRbG9X3QRqcrno5FyMw4NmCUfFyXQPXbAZD3NYZntt29VSMVKEj3I%3D/3/full.json?AWSAccessKeyId=AKIAJRDFEY23UEVW42BQ&Expires=1445727776&Signature=ZXRUldeRN8OR7XPMjkYnZZWhSE8%3D", "energy": 0.883254, "liveness": 0.17135, "tempo": 140.344, "speechiness": 0.067975, "acousticness": 0.002654, "danceability": 0.325249, "instrumentalness": 1e-06, "key": 0, "duration": 247.65333, "loudness": -3.445, "audio_md5": "", "valence": 0.052604, "mode": 1}}, {"song_hotttnesss": 0.080559, "title": "Control the Spectrum", "artist_discovery": 0.30380302757697875, "artist_name": "The Sound Capsule", "song_type": ["electric"], "artist_hotttnesss": 0.317377, "artist_location": {"latitude": 37.7796, "location": "San Francisco, CA, US", "longitude": -122.42}, "song_currency": 0.0007500000000000001, "artist_familiarity": 0.19278, "artist_id": "ARVMABH122988FBF4F", "id": "SOBJVLD13CF6AEE34C", "audio_summary": {"time_signature": 4, "analysis_url": "http://echonest-analysis.s3.amazonaws.com/TR/zpKIEAvwtdPfH4wRDA5_XH2EF9_3ym7R5eXnZitZbT3fmb8Xh08GUr4lyykfcAzK6zDsCGPOTz5CHDw_w%3D/3/full.json?AWSAccessKeyId=AKIAJRDFEY23UEVW42BQ&Expires=1445727776&Signature=NNgWK/tq3JApKQ7mMsSdCGv9obM%3D", "energy": 0.513839, "liveness": 0.707433, "tempo": 103.988, "speechiness": 0.058715, "acousticness": 0.022909, "danceability": 0.726628, "instrumentalness": 0.84668, "key": 7, "duration": 208.69333, "loudness": -14.088, "audio_md5": "", "valence": 0.313998, "mode": 1}}]}}