{"response": {"status": {"code": 0, "message": "Success", "version": "4.2"}, "songs": [{"song_hotttnesss": 0.302695, "song_currency_rank": 209525, "artist_discovery_rank": 1382, "title": "Ode To My Thalamus", "artist_discovery": 0.6015146322683563, "song_hotttnesss_rank": 150688, "artist_name": "Asaf Avidan", "song_type": ["studio", "electric", "vocal"], "artist_hotttnesss": 0.748955, "artist_familiarity_rank": 8069, "artist_location": {"latitude": 31.78, "location": "Jerusalem, Israel", "longitude": 35.23}, "song_currency": 0.002593433230498017, "id": "SOTZSDQ14A5945C6DC", "artist_familiarity": 0.524646, "artist_id": "AR8T7IU11C8A4221A0", "artist_hotttnesss_rank": 833, "audio_summary": {"time_signature": 4, "analysis_url": "http://echonest-analysis.s3.amazonaws.com/TR/jZHvzw_8nGxBdCBtlvuHFb3yg_5Ima_ehYetmXI5Rir-y1dQy22V3KnJSJhYE5ezD32n1M3_Mz3Gudxjs%3D/3/full.json?AWSAccessKeyId=AKIAJRDFEY23UEVW42BQ&Expires=1445735198&Signature=ZK50BWd8eLJrbPtmLBp5FtOEs7E%3D", "energy": 0.663814, "liveness": 0.062317, "tempo": 124.905, "speechiness": 0.036419, "acousticness": 0.150685, "danceability": 0.650771, "instrumentalness": 4e-06, "key": 10, "duration": 218.17465, "loudness": -7.276, "audio_md5": "", "valence": 0.687614, "mode": 1}}]}}