{"response": {"status": {"code": 0, "message": "Success", "version": "4.2"}, "songs": [{"song_hotttnesss": 0.547847, "song_currency_rank": 6145, "artist_discovery_rank": 1224, "title": "Moments", "artist_discovery": 0.6113122072601869, "song_hotttnesss_rank": 2055, "artist_name": "Tove Lo", "song_type": ["studio", "electric", "vocal"], "artist_hotttnesss": 0.883544, "artist_familiarity_rank": 2385, "artist_location": {"latitude": 59.3333333, "location": "stockholm, sweden", "longitude": 18.05}, "song_currency": 0.07466615795497901, "id": "SOMOHNI1486E20DB46", "artist_familiarity": 0.619584, "artist_id": "ARBUIGY13A709C567F", "artist_hotttnesss_rank": 71, "audio_summary": {"time_signature": 4, "analysis_url": "http://echonest-analysis.s3.amazonaws.com/TR/c3HImgRmFUIIYoE0pGyoc7o32rQrHzbdIw50fJTwIKZWjC36qRYeGs4cSY4ctHo4LfDTrsemkuSqtLS_Y%3D/3/full.json?AWSAccessKeyId=AKIAJRDFEY23UEVW42BQ&Expires=1445725484&Signature=az/B6gnlAab3nELPpXdxeKrg0/g%3D", "energy": 0.879428, "liveness": 0.338337, "tempo": 126.005, "speechiness": 0.049372, "acousticness": 0.171745, "danceability": 0.708213, "instrumentalness": 0.002869, "key": 0, "duration": 202.34667, "loudness": -4.925, "audio_md5": "", "valence": 0.72039, "mode": 1}}, {"song_hotttnesss": 0.0, "artist_discovery_rank": 1224, "title": "Moments", "artist_discovery": 0.6113122072601869, "artist_hotttnesss_rank": 71, "artist_name": "Tove Lo", "song_type": ["studio", "electric", "vocal"], "artist_hotttnesss": 0.883544, "artist_familiarity_rank": 2385, "artist_location": {"latitude": 59.3333333, "location": "stockholm, sweden", "longitude": 18.05}, "song_currency": 0.0, "artist_familiarity": 0.619584, "artist_id": "ARBUIGY13A709C567F", "id": "SOQNKSD1508D2DD8FF", "audio_summary": {"time_signature": 4, "analysis_url": "http://echonest-analysis.s3.amazonaws.com/TR/i1uykAcKLtbJR4Ckwc2cWhm14eyLXF7ZYA-_8qN_7xtwj4jiYBvBzpYcnIDbYTNxy2tn_G/3/full.json?AWSAccessKeyId=AKIAJRDFEY23UEVW42BQ&Expires=1445725484&Signature=itZE37sT6H3S2Ufh62DDUyus40I%3D", "energy": 0.513411, "liveness": 0.321763, "tempo": 128.547, "speechiness": 0.066476, "acousticness": 0.052611, "danceability": 0.652267, "instrumentalness": 3e-06, "key": 0, "duration": 192.9922, "loudness": -17.429, "audio_md5": "201ae673f8af617d6a51a45ab6b50932", "valence": 0.504181, "mode": 1}}]}}