{"response": {"status": {"code": 0, "message": "Success", "version": "4.2"}, "songs": [{"song_hotttnesss": 0.315063, "title": "Oh!", "artist_discovery": 0.43822424664793275, "artist_name": "We Have Band", "song_type": ["studio", "electric", "vocal"], "artist_hotttnesss": 0.535314, "artist_location": {"latitude": 51.5063, "location": "London, England, GB", "longitude": -0.12714}, "song_currency": 0.001562894887995405, "artist_familiarity": 0.511629, "artist_id": "ARIDXDZ11C8A414C98", "id": "SOAZYHB14A45C1F2EF", "audio_summary": {"time_signature": 4, "analysis_url": "http://echonest-analysis.s3.amazonaws.com/TR/Pg0mvg_mBXjeXd3ZznIOSrZice3dZio_zguRBh9cyZnO5NcI18xCEW79Yc-D_mxFgr93HPmKgcvqYKk_s%3D/3/full.json?AWSAccessKeyId=AKIAJRDFEY23UEVW42BQ&Expires=1445727229&Signature=g0jAMwD8YNil1dkv0/7IDYsGfzg%3D", "energy": 0.824883, "liveness": 0.094543, "tempo": 124.003, "speechiness": 0.044478, "acousticness": 0.096032, "danceability": 0.723751, "instrumentalness": 0.000745, "key": 5, "duration": 204.32884, "loudness": -4.885, "audio_md5": "03a7abf4b6d29ce4a4be8b9a74b3b6df", "valence": 0.751006, "mode": 1}}, {"song_hotttnesss": 0.315063, "title": "Oh!", "artist_discovery": 0.43822424664793275, "artist_name": "We Have Band", "song_type": ["studio", "electric", "vocal"], "artist_hotttnesss": 0.535314, "artist_location": {"latitude": 51.5063, "location": "London, England, GB", "longitude": -0.12714}, "song_currency": 0.001562894887995405, "artist_familiarity": 0.511629, "artist_id": "ARIDXDZ11C8A414C98", "id": "SOJARTM14A45C201FE", "audio_summary": {"time_signature": 4, "analysis_url": "http://echonest-analysis.s3.amazonaws.com/TR/LQDvSwZmj3vqhOc96pG0gpRb0ZVlw4yoPav_VKd0a2Wd6IKBhhl6j83QuHih9cEb7aOFpuesJ6BZ0MkJU%3D/3/full.json?AWSAccessKeyId=AKIAJRDFEY23UEVW42BQ&Expires=1445727229&Signature=57okxAkhbzuWaA8wFAMCAqTkndI%3D", "energy": 0.932387, "liveness": 0.28772, "tempo": 141.973, "speechiness": 0.031804, "acousticness": 0.042331, "danceability": 0.670275, "instrumentalness": 0.069782, "key": 9, "duration": 187.31211, "loudness": -4.855, "audio_md5": "95f4268de055c1763c9441bf7a87e21b", "valence": 0.920962, "mode": 0}}, {"song_hotttnesss": 0.263769, "song_currency_rank": 320415, "artist_discovery_rank": 63203, "title": "Oh!", "artist_discovery": 0.43822424664793275, "song_hotttnesss_rank": 256463, "artist_name": "We Have Band", "song_type": ["instrumental", "studio", "electric"], "artist_hotttnesss": 0.535314, "artist_familiarity_rank": 9470, "artist_location": {"latitude": 51.5063, "location": "London, England, GB", "longitude": -0.12714}, "song_currency": 0.001562894887995405, "id": "SOALYOE136A986FDAB", "artist_familiarity": 0.511629, "artist_id": "ARIDXDZ11C8A414C98", "artist_hotttnesss_rank": 18804, "audio_summary": {"time_signature": 4, "analysis_url": "http://echonest-analysis.s3.amazonaws.com/TR/TRJVXNV12BBFF6F62C/3/full.json?AWSAccessKeyId=AKIAJRDFEY23UEVW42BQ&Expires=1445727229&Signature=o4xAJbfNMq7ak%2BHMdF8ZgCi0Sco%3D", "energy": 0.91961, "liveness": 0.238574, "tempo": 142.009, "speechiness": 0.029088, "acousticness": 0.127621, "danceability": 0.652916, "instrumentalness": 0.963303, "key": 1, "duration": 222.17098, "loudness": -5.803, "audio_md5": "6d70da552782f585d10d05df0390d9d6", "valence": 0.948523, "mode": 0}}, {"song_hotttnesss": 0.315063, "song_currency_rank": 320415, "artist_discovery_rank": 63203, "title": "Oh!", "artist_discovery": 0.43822424664793275, "song_hotttnesss_rank": 126016, "artist_name": "We Have Band", "song_type": ["studio", "electric"], "artist_hotttnesss": 0.535314, "artist_familiarity_rank": 9470, "artist_location": {"latitude": 51.5063, "location": "London, England, GB", "longitude": -0.12714}, "song_currency": 0.001562894887995405, "id": "SOJVZYZ13134393821", "artist_familiarity": 0.511629, "artist_id": "ARIDXDZ11C8A414C98", "artist_hotttnesss_rank": 18804, "audio_summary": {"time_signature": 4, "analysis_url": "http://echonest-analysis.s3.amazonaws.com/TR/45X9Kg3rMusW6i_XVQrjAcfzrIFZsEykn-JkzRFPvVQ-8rjfuzI5yPFFZ-sVL7s4Gh6Dn87biWUo07jcw%3D/3/full.json?AWSAccessKeyId=AKIAJRDFEY23UEVW42BQ&Expires=1445727229&Signature=G9tgRPHBhWevk9KaTvTtxTG2p/Y%3D", "energy": 0.921634, "liveness": 0.296397, "tempo": 141.967, "speechiness": 0.026812, "acousticness": 0.007733, "danceability": 0.635833, "instrumentalness": 0.66924, "key": 9, "duration": 187.66667, "loudness": -4.869, "audio_md5": "", "valence": 0.969127, "mode": 0}}, {"song_hotttnesss": 0.0, "title": "Oh! (Bit Funk remix)", "artist_discovery": 0.43822424664793275, "artist_name": "We Have Band", "song_type": ["remix", "studio", "electric", "vocal"], "artist_hotttnesss": 0.535314, "artist_location": {"latitude": 51.5063, "location": "London, England, GB", "longitude": -0.12714}, "song_currency": 0.0, "artist_familiarity": 0.511629, "artist_id": "ARIDXDZ11C8A414C98", "id": "SOWHTUD1412D5F2374", "audio_summary": {"time_signature": 4, "analysis_url": "http://echonest-analysis.s3.amazonaws.com/TR/Kx2PDQ_GBkcW2B4c1qUkO0aIEonYhWX05lR43rUIDI_tjWEZk%3D/3/full.json?AWSAccessKeyId=AKIAJRDFEY23UEVW42BQ&Expires=1445727229&Signature=s65T%2BDXrF61cRrA8DN9ToO14gFc%3D", "energy": 0.745206, "liveness": 0.088225, "tempo": 124.027, "speechiness": 0.046545, "acousticness": 0.102178, "danceability": 0.719381, "instrumentalness": 0.035861, "key": 5, "duration": 310.84508, "loudness": -6.287, "audio_md5": "42e6624e9409e7731eb98452c6d0a0ed", "valence": 0.793229, "mode": 1}}, {"song_hotttnesss": 0.0, "title": "Oh! (Dam Mantle Remix)", "artist_discovery": 0.43822424664793275, "artist_name": "We Have Band", "song_type": ["remix", "studio", "electric", "vocal"], "artist_hotttnesss": 0.535314, "artist_location": {"latitude": 51.5063, "location": "London, England, GB", "longitude": -0.12714}, "song_currency": 0.0, "artist_familiarity": 0.511629, "artist_id": "ARIDXDZ11C8A414C98", "id": "SOHGRDP14472A5166C", "audio_summary": {"time_signature": 4, "analysis_url": "http://echonest-analysis.s3.amazonaws.com/TR/cKpuYg7dO_Q0U4cJywhxlL4v-22jp_bOZKRxn70iNhIAYTCV68jxT7gH-7rUbvMEraTO55Sxjwp48B-wQ%3D/3/full.json?AWSAccessKeyId=AKIAJRDFEY23UEVW42BQ&Expires=1445727229&Signature=tWGu6oBd7aftSRssVGu/PY6A/Hk%3D", "energy": 0.783519, "liveness": 0.062663, "tempo": 141.935, "speechiness": 0.068589, "acousticness": 0.023423, "danceability": 0.636415, "instrumentalness": 0.000815, "key": 11, "duration": 258.26785, "loudness": -5.257, "audio_md5": "", "valence": 0.139673, "mode": 0}}, {"song_hotttnesss": 0.0, "title": "Oh! (Filthy Dukes remix)", "artist_discovery": 0.43822424664793275, "artist_name": "We Have Band", "song_type": ["remix", "studio", "electric"], "artist_hotttnesss": 0.535314, "artist_location": {"latitude": 51.5063, "location": "London, England, GB", "longitude": -0.12714}, "song_currency": 0.0, "artist_familiarity": 0.511629, "artist_id": "ARIDXDZ11C8A414C98", "id": "SOUEMCI1412D6072CE", "audio_summary": {"time_signature": 4, "analysis_url": "http://echonest-analysis.s3.amazonaws.com/TR/WyF5MAzqTdR5f2VEnYt0bWzMT-UV5ZdDvydAdcnM5azpYr9E4%3D/3/full.json?AWSAccessKeyId=AKIAJRDFEY23UEVW42BQ&Expires=1445727229&Signature=35bNJnu5yhhye4G/YlaRENcFoa8%3D", "energy": 0.927108, "liveness": 0.126405, "tempo": 127.991, "speechiness": 0.033577, "acousticness": 0.00408, "danceability": 0.768828, "instrumentalness": 0.784271, "key": 2, "duration": 392.88118, "loudness": -6.174, "audio_md5": "b5a3043aa4b35a87b92d07f1e54eb218", "valence": 0.926076, "mode": 1}}, {"song_hotttnesss": 0.0443, "title": "Oh! (Plugs Remix)", "artist_discovery": 0.43822424664793275, "artist_name": "We Have Band", "song_type": ["remix", "studio", "electric", "vocal"], "artist_hotttnesss": 0.535314, "artist_location": {"latitude": 51.5063, "location": "London, England, GB", "longitude": -0.12714}, "song_currency": 4.1666666666666665e-05, "artist_familiarity": 0.511629, "artist_id": "ARIDXDZ11C8A414C98", "id": "SOHLUJL14A45C1FD91", "audio_summary": {"time_signature": 4, "analysis_url": "http://echonest-analysis.s3.amazonaws.com/TR/wXRe-AF4ytfLfloF-SdBHx1DLWvxlyHPQ7HKSFucXlkNeomoxC0im6A3P-nFyKYbbQJFwwiltQezON4Lo%3D/3/full.json?AWSAccessKeyId=AKIAJRDFEY23UEVW42BQ&Expires=1445727229&Signature=38OZnekuk0vxlZaAnBc6v%2BEij9o%3D", "energy": 0.77543, "liveness": 0.08341, "tempo": 141.972, "speechiness": 0.044192, "acousticness": 0.046916, "danceability": 0.564509, "instrumentalness": 0.002322, "key": 9, "duration": 260.14059, "loudness": -5.885, "audio_md5": "", "valence": 0.396366, "mode": 0}}, {"song_hotttnesss": 0.0443, "title": "Oh! (Radio edit)", "artist_discovery": 0.43822424664793275, "artist_name": "We Have Band", "song_type": ["studio", "electric", "vocal"], "artist_hotttnesss": 0.535314, "artist_location": {"latitude": 51.5063, "location": "London, England, GB", "longitude": -0.12714}, "song_currency": 1.1904761904761905e-05, "artist_familiarity": 0.511629, "artist_id": "ARIDXDZ11C8A414C98", "id": "SOPSSRU13134386357", "audio_summary": {"time_signature": 4, "analysis_url": "http://echonest-analysis.s3.amazonaws.com/TR/3zl0GQnYqgb6oeuV8bj1mbSmaOIuQHybYw1zM6x9pX3gw125rXRMj_sPLzH7Ds2IwUo9gao_RqJ9hZ7dg%3D/3/full.json?AWSAccessKeyId=AKIAJRDFEY23UEVW42BQ&Expires=1445727229&Signature=bfDLBE/8a/d3nIahf/vRJS9bFRo%3D", "energy": 0.935185, "liveness": 0.284749, "tempo": 141.976, "speechiness": 0.031357, "acousticness": 0.036622, "danceability": 0.668118, "instrumentalness": 0.050502, "key": 9, "duration": 187.31256, "loudness": -4.784, "audio_md5": "", "valence": 0.92952, "mode": 0}}, {"song_hotttnesss": 0.0443, "title": "Oh! (Plugs Remix)", "artist_discovery": 0.43822424664793275, "artist_name": "We Have Band", "song_type": ["remix", "studio", "electric", "vocal"], "artist_hotttnesss": 0.535314, "artist_location": {"latitude": 51.5063, "location": "London, England, GB", "longitude": -0.12714}, "song_currency": 4.1666666666666665e-05, "artist_familiarity": 0.511629, "artist_id": "ARIDXDZ11C8A414C98", "id": "SOVUFRP1373FDF0D05", "audio_summary": {"time_signature": 4, "analysis_url": "http://echonest-analysis.s3.amazonaws.com/TR/kYR6-Aod3vME1vyP9f1JYc8zLKbCAFcajd6O-LPciw4ydMIDpDwXD_67n754BDcQvOi7cT2Y9pjWVe6gk%3D/3/full.json?AWSAccessKeyId=AKIAJRDFEY23UEVW42BQ&Expires=1445727229&Signature=2/DTggYE%2BvJ%2BmsnDaavX41MWRKs%3D", "energy": 0.784008, "liveness": 0.058281, "tempo": 141.999, "speechiness": 0.048613, "acousticness": 0.067137, "danceability": 0.625106, "instrumentalness": 0.139971, "key": 9, "duration": 261.66667, "loudness": -4.827, "audio_md5": "", "valence": 0.341635, "mode": 0}}, {"song_hotttnesss": 0.0, "title": "Oh! (Prizes Remix)", "artist_discovery": 0.43822424664793275, "artist_name": "We Have Band", "song_type": ["remix", "studio", "electric", "vocal"], "artist_hotttnesss": 0.535314, "artist_location": {"latitude": 51.5063, "location": "London, England, GB", "longitude": -0.12714}, "song_currency": 0.0, "artist_familiarity": 0.511629, "artist_id": "ARIDXDZ11C8A414C98", "id": "SOBFFZS14A45C2665A", "audio_summary": {"time_signature": 4, "analysis_url": "http://echonest-analysis.s3.amazonaws.com/TR/tzDs4gorYAws9Jm8Rw-cqnqQfuvc87rM9a6cuDL6RMX3ZwgtexkvEvgQmI8pPDvW9IFJMBcDHpUTVTueg%3D/3/full.json?AWSAccessKeyId=AKIAJRDFEY23UEVW42BQ&Expires=1445727229&Signature=6FOdrpw2a8jGdmgBNDU4vGL4Vvg%3D", "energy": 0.788505, "liveness": 0.242644, "tempo": 140.889, "speechiness": 0.041578, "acousticness": 0.04738, "danceability": 0.435046, "instrumentalness": 1e-06, "key": 2, "duration": 218.27052, "loudness": -5.636, "audio_md5": "", "valence": 0.375203, "mode": 0}}, {"song_hotttnesss": 0.102861, "title": "Oh! (Bit Funk remix radio edit)", "artist_discovery": 0.43822424664793275, "artist_name": "We Have Band", "song_type": ["remix", "studio", "electric", "vocal"], "artist_hotttnesss": 0.535314, "artist_location": {"latitude": 51.5063, "location": "London, England, GB", "longitude": -0.12714}, "song_currency": 0.00017391304347826088, "artist_familiarity": 0.511629, "artist_id": "ARIDXDZ11C8A414C98", "id": "SORUPIP1312A8A6FED", "audio_summary": {"time_signature": 4, "analysis_url": "http://echonest-analysis.s3.amazonaws.com/TR/5jTRNgjOnzEDmMfuu05bopzYmEYG43phdjkDHQrTwXaV1Pq90axeQpq-6lllI9s7xvzgSUGrbQxvR-77Y%3D/3/full.json?AWSAccessKeyId=AKIAJRDFEY23UEVW42BQ&Expires=1445727229&Signature=xFPqLqJxvUm1S/LUPkAGAP2gzac%3D", "energy": 0.824489, "liveness": 0.097475, "tempo": 124.02, "speechiness": 0.045113, "acousticness": 0.103958, "danceability": 0.724614, "instrumentalness": 0.000924, "key": 5, "duration": 204.32925, "loudness": -4.826, "audio_md5": "", "valence": 0.752111, "mode": 1}}, {"song_hotttnesss": 0.0443, "song_currency_rank": 5662422, "artist_discovery_rank": 63203, "title": "Oh! (Vicarious Bliss Love Dove Remix)", "artist_discovery": 0.43822424664793275, "song_hotttnesss_rank": 3687122, "artist_name": "We Have Band", "song_type": ["remix", "studio", "electric", "vocal"], "artist_hotttnesss": 0.535314, "artist_familiarity_rank": 9470, "artist_location": {"latitude": 51.5063, "location": "London, England, GB", "longitude": -0.12714}, "song_currency": 2.5e-05, "id": "SOUSWJG131343887DD", "artist_familiarity": 0.511629, "artist_id": "ARIDXDZ11C8A414C98", "artist_hotttnesss_rank": 18804, "audio_summary": {"time_signature": 4, "analysis_url": "http://echonest-analysis.s3.amazonaws.com/TR/TPAEbwTxGRWRPGxe04OQ50DHSaFdrXpwtyAX4aA59usuQb8nkdJYmfVBVHDtEuGyZXo3RYO_TM_1VtNBI%3D/3/full.json?AWSAccessKeyId=AKIAJRDFEY23UEVW42BQ&Expires=1445727229&Signature=oMIl1700//1IhwqBvMhvllsjzY8%3D", "energy": 0.865723, "liveness": 0.211232, "tempo": 130.017, "speechiness": 0.027635, "acousticness": 0.002699, "danceability": 0.615008, "instrumentalness": 0.117372, "key": 2, "duration": 343.95329, "loudness": -6.638, "audio_md5": "", "valence": 0.290086, "mode": 1}}, {"song_hotttnesss": 0.0, "title": "Oh, To Be A Saint", "artist_name": "What If This Dream Is All We Have?", "song_type": ["studio", "electric", "vocal"], "artist_hotttnesss": 0.0, "artist_location": {"latitude": 43.466171, "location": "Oakville,Canada", "longitude": -79.689583}, "song_currency": 0.0, "artist_familiarity": 0.116932, "artist_id": "ARXPJRT12FE0869EFA", "id": "SOFYSDI13134385E40", "audio_summary": {"time_signature": 4, "analysis_url": "http://echonest-analysis.s3.amazonaws.com/TR/qVDYywW66Yu1sj3AJrmzw-g8lHOuvUbOjU9ZZk/3/full.json?AWSAccessKeyId=AKIAJRDFEY23UEVW42BQ&Expires=1445727229&Signature=TOKjeAYhRTkyYSjcTXWmj4LHC2k%3D", "energy": 0.528679, "liveness": 0.131487, "tempo": 79.068, "speechiness": 0.030385, "acousticness": 0.030552, "danceability": 0.229835, "instrumentalness": 0.0, "key": 4, "duration": 293.68, "loudness": -6.446, "audio_md5": "60dba7c459fb0ea6f1e919d3b59c5b5a", "valence": 0.237987, "mode": 1}}]}}