{"response": {"status": {"code": 0, "message": "Success", "version": "4.2"}, "songs": [{"song_hotttnesss": 0.282412, "song_currency_rank": 181351, "artist_discovery_rank": 5857, "title": "Slaver", "artist_discovery": 0.5246445843756667, "song_hotttnesss_rank": 200513, "artist_name": "Pompeya", "song_type": ["studio", "electric"], "artist_hotttnesss": 0.615554, "artist_familiarity_rank": 13488, "artist_location": {"latitude": 55.757, "location": "Moscow, Moscow Federal City, RU", "longitude": 37.615}, "song_currency": 0.003059326563335115, "id": "SOQQVHP14241A32E32", "artist_familiarity": 0.483629, "artist_id": "ARJYLWG11E2835D029", "artist_hotttnesss_rank": 4228, "audio_summary": {"time_signature": 4, "analysis_url": "http://echonest-analysis.s3.amazonaws.com/TR/srWfVg4FESw8GQCP5b6BlSuvMQ_C6l6NwAwXF_ZZUZfHSG0G9MiIrmly6dfNmOWH5vnmW-06nCYQZ48dw%3D/3/full.json?AWSAccessKeyId=AKIAJRDFEY23UEVW42BQ&Expires=1445739398&Signature=tL67cPx0oOH8yf8HA5qaIrYIMZk%3D", "energy": 0.821687, "liveness": 0.107192, "tempo": 97.973, "speechiness": 0.027043, "acousticness": 0.045144, "danceability": 0.598598, "instrumentalness": 0.508606, "key": 0, "duration": 259.65714, "loudness": -7.117, "audio_md5": "", "valence": 0.862418, "mode": 1}}, {"song_hotttnesss": 0.102861, "title": "Slaver (Psychemagik Remix)", "artist_discovery": 0.5246445843756667, "artist_name": "Pompeya", "song_type": ["remix", "studio", "electric", "vocal"], "artist_hotttnesss": 0.615554, "artist_location": {"latitude": 55.757, "location": "Moscow, Moscow Federal City, RU", "longitude": 37.615}, "song_currency": 6.504065040650407e-05, "artist_familiarity": 0.483629, "artist_id": "ARJYLWG11E2835D029", "id": "SOMOEMC1444FF9CB69", "audio_summary": {"time_signature": 4, "analysis_url": "http://echonest-analysis.s3.amazonaws.com/TR/ejCVZgPFhUR7lz7DXZ1uZU2HZXuA4wUjSc68s9ttlY_EpGeFWLYiRhrQ5RSRho2ZP-roPsAzLaPcZSsBY%3D/3/full.json?AWSAccessKeyId=AKIAJRDFEY23UEVW42BQ&Expires=1445739399&Signature=O36hUa/SH3jyvy7ZTgpJzGWNUb4%3D", "energy": 0.602102, "liveness": 0.112987, "tempo": 98.014, "speechiness": 0.030563, "acousticness": 0.170712, "danceability": 0.754101, "instrumentalness": 0.337731, "key": 0, "duration": 427.44816, "loudness": -6.822, "audio_md5": "", "valence": 0.448199, "mode": 1}}]}}