{"response": {"status": {"code": 0, "message": "Success", "version": "4.2"}, "songs": [{"song_hotttnesss": 0.0, "song_currency_rank": 13124, "artist_discovery_rank": 189188, "title": "Little Secrets", "artist_discovery": 0.3739098292227674, "artist_name": "Passion Pit", "song_type": ["studio", "electric", "vocal"], "artist_hotttnesss": 0.627164, "artist_familiarity_rank": 747, "artist_location": {"latitude": 42.3668, "location": "Cambridge, MA, US", "longitude": -71.106}, "song_currency": 0.051535573537299165, "id": "SOMMDCV13D5FB5D229", "artist_familiarity": 0.700862, "artist_id": "AR6PFD411C8A416424", "artist_hotttnesss_rank": 3575, "audio_summary": {"time_signature": 4, "analysis_url": "http://echonest-analysis.s3.amazonaws.com/TR/L51wmAccA4OFWu3joRcaODW-Gxbs6KpTchEPffwHjpYNohm18h_8LIf4m-wZ-1gXMZknnqjWzczvS7xHk%3D/3/full.json?AWSAccessKeyId=AKIAJRDFEY23UEVW42BQ&Expires=1445727099&Signature=M3RAl6Uc%2BV8RoRMZHLKSUAyKYWg%3D", "energy": 0.798174, "liveness": 0.183677, "tempo": 105.69, "speechiness": 0.042628, "acousticness": 0.003191, "danceability": 0.574902, "instrumentalness": 0.0, "key": 0, "duration": 222.05333, "loudness": -5.96, "audio_md5": "", "valence": 0.565209, "mode": 1}}, {"song_hotttnesss": 0.555614, "song_currency_rank": 13124, "artist_discovery_rank": 189188, "title": "Little Secrets", "artist_discovery": 0.3739098292227674, "song_hotttnesss_rank": 1787, "artist_name": "Passion Pit", "song_type": ["studio", "electric", "vocal"], "artist_hotttnesss": 0.627164, "artist_familiarity_rank": 747, "artist_location": {"latitude": 42.3668, "location": "Cambridge, MA, US", "longitude": -71.106}, "song_currency": 0.051535573537299165, "id": "SOUFDBW137AD745F34", "artist_familiarity": 0.700862, "artist_id": "AR6PFD411C8A416424", "artist_hotttnesss_rank": 3575, "audio_summary": {"time_signature": 4, "analysis_url": "http://echonest-analysis.s3.amazonaws.com/TR/-2L_bwj9zpKfGX3yPqsH8yECuNMWYo2vbbmfNaSWsQgXdHBE4P4V3seYJ2AXPfHt9K6A5bbY0MbwUCEcc%3D/3/full.json?AWSAccessKeyId=AKIAJRDFEY23UEVW42BQ&Expires=1445727099&Signature=cTLvCfiY8qq%2B011BKjO%2BSHxwZ2Y%3D", "energy": 0.860013, "liveness": 0.206017, "tempo": 127.697, "speechiness": 0.102591, "acousticness": 0.001714, "danceability": 0.712814, "instrumentalness": 0.288084, "key": 9, "duration": 272.90621, "loudness": -9.385, "audio_md5": "4aeac541e1116471ad1ef90782119efa", "valence": 0.277104, "mode": 1}}, {"song_hotttnesss": 0.555614, "song_currency_rank": 13124, "artist_discovery_rank": 189188, "title": "Little Secrets", "artist_discovery": 0.3739098292227674, "song_hotttnesss_rank": 1787, "artist_name": "Passion Pit", "song_type": ["studio", "electric", "vocal"], "artist_hotttnesss": 0.627164, "artist_familiarity_rank": 747, "artist_location": {"latitude": 42.3668, "location": "Cambridge, MA, US", "longitude": -71.106}, "song_currency": 0.051535573537299165, "id": "SOKIENC146176CD7CD", "artist_familiarity": 0.700862, "artist_id": "AR6PFD411C8A416424", "artist_hotttnesss_rank": 3575, "audio_summary": {"time_signature": 4, "analysis_url": "http://echonest-analysis.s3.amazonaws.com/TR/m9DdYQyRQgikXb8R6MlulCLp460UiQO_YLSlX3/3/full.json?AWSAccessKeyId=AKIAJRDFEY23UEVW42BQ&Expires=1445727099&Signature=6jlpiOWSmT3KMS4MhGJdn9MhzOY%3D", "energy": 0.47837, "liveness": 0.026695, "tempo": 99.904, "speechiness": 0.042663, "acousticness": 0.003048, "danceability": 0.583113, "instrumentalness": 2e-06, "key": 0, "duration": 247.10354, "loudness": -16.097, "audio_md5": "26ba7859f5bc9067444e37a659a9d306", "valence": 0.708509, "mode": 0}}, {"song_hotttnesss": 0.555614, "song_currency_rank": 13124, "artist_discovery_rank": 189188, "title": "Little Secrets", "artist_discovery": 0.3739098292227674, "song_hotttnesss_rank": 1787, "artist_name": "Passion Pit", "song_type": ["studio", "electric", "vocal"], "artist_hotttnesss": 0.627164, "artist_familiarity_rank": 747, "artist_location": {"latitude": 42.3668, "location": "Cambridge, MA, US", "longitude": -71.106}, "song_currency": 0.051535573537299165, "id": "SOHYXNC146172C01A4", "artist_familiarity": 0.700862, "artist_id": "AR6PFD411C8A416424", "artist_hotttnesss_rank": 3575, "audio_summary": {"time_signature": 4, "analysis_url": "http://echonest-analysis.s3.amazonaws.com/TR/kpwqdQTZkPZX61Io-vAYSObIHW3Yyv1LgBiCLIsIPnYREEH_dPhwS363sQaz7pA_QUubr-xHVbsaEtEm0%3D/3/full.json?AWSAccessKeyId=AKIAJRDFEY23UEVW42BQ&Expires=1445727099&Signature=s3e2ofv94OSB4iUBippE7PNbGDY%3D", "energy": 0.795426, "liveness": 0.11913, "tempo": 99.898, "speechiness": 0.041433, "acousticness": 0.003835, "danceability": 0.59759, "instrumentalness": 1e-06, "key": 5, "duration": 238.02667, "loudness": -4.353, "audio_md5": "", "valence": 0.670382, "mode": 1}}, {"song_hotttnesss": 0.555614, "song_currency_rank": 13124, "artist_discovery_rank": 189188, "title": "Little Secrets", "artist_discovery": 0.3739098292227674, "song_hotttnesss_rank": 1787, "artist_name": "Passion Pit", "song_type": ["studio", "electric", "vocal"], "artist_hotttnesss": 0.627164, "artist_familiarity_rank": 747, "artist_location": {"latitude": 42.3668, "location": "Cambridge, MA, US", "longitude": -71.106}, "song_currency": 0.051535573537299165, "id": "SOIRRHW136ECDCDEE4", "artist_familiarity": 0.700862, "artist_id": "AR6PFD411C8A416424", "artist_hotttnesss_rank": 3575, "audio_summary": {"time_signature": 4, "analysis_url": "http://echonest-analysis.s3.amazonaws.com/TR/hKwg6wxdumj8elk3drSTHzRH_Dn5ow0iBupxq-X6xYR7gPIB76uwdxYDaeJzQe031l3Nzb-xLrtgE5V64%3D/3/full.json?AWSAccessKeyId=AKIAJRDFEY23UEVW42BQ&Expires=1445727099&Signature=/u8Yvkg6xEkRqO1A%2BSao7t7Pngk%3D", "energy": 0.870213, "liveness": 0.356216, "tempo": 129.019, "speechiness": 0.05053, "acousticness": 0.002092, "danceability": 0.50523, "instrumentalness": 0.206154, "key": 9, "duration": 272.21333, "loudness": -6.915, "audio_md5": "", "valence": 0.18282, "mode": 1}}, {"song_hotttnesss": 0.555614, "song_currency_rank": 13124, "artist_discovery_rank": 189188, "title": "Little Secrets", "artist_discovery": 0.3739098292227674, "song_hotttnesss_rank": 1787, "artist_name": "Passion Pit", "song_type": ["studio", "electric", "vocal"], "artist_hotttnesss": 0.627164, "artist_familiarity_rank": 747, "artist_location": {"latitude": 42.3668, "location": "Cambridge, MA, US", "longitude": -71.106}, "song_currency": 0.051535573537299165, "id": "SOUQXQZ13C83652CF7", "artist_familiarity": 0.700862, "artist_id": "AR6PFD411C8A416424", "artist_hotttnesss_rank": 3575, "audio_summary": {"time_signature": 4, "analysis_url": "http://echonest-analysis.s3.amazonaws.com/TR/IaqzxQxugSa1iRsrtK-lJz3TFHuPJ5N348xt657ZqLIRJNIqKvawY9yi6Sxyi_bVo3OYCeBVZC0Iygrdc%3D/3/full.json?AWSAccessKeyId=AKIAJRDFEY23UEVW42BQ&Expires=1445727099&Signature=EnTdxo3Sh2d1GetG%2BG29O1osWTo%3D", "energy": 0.822418, "liveness": 0.32242, "tempo": 129.608, "speechiness": 0.06591, "acousticness": 0.000568, "danceability": 0.673976, "instrumentalness": 0.279857, "key": 9, "duration": 256.31955, "loudness": -10.396, "audio_md5": "40fe48067b4f8193a3417eb95801385f", "valence": 0.28545, "mode": 1}}, {"song_hotttnesss": 0.0, "title": "Little Secrets (UK Version)", "artist_discovery": 0.3739098292227674, "artist_name": "Passion Pit", "song_type": ["remix", "studio", "electric", "vocal"], "artist_hotttnesss": 0.627164, "artist_location": {"latitude": 42.3668, "location": "Cambridge, MA, US", "longitude": -71.106}, "song_currency": 0.0, "artist_familiarity": 0.700862, "artist_id": "AR6PFD411C8A416424", "id": "SOGWLEH13E907F1326", "audio_summary": {"time_signature": 4, "analysis_url": "http://echonest-analysis.s3.amazonaws.com/TR/Q6dzGw0OHUCX-LxUegeWanYCoVazn_P4VL-lJ3/3/full.json?AWSAccessKeyId=AKIAJRDFEY23UEVW42BQ&Expires=1445727099&Signature=epn2167zJdhjEFhBbki%2BxnGn15I%3D", "energy": 0.496034, "liveness": 0.635064, "tempo": 99.934, "speechiness": 0.048065, "acousticness": 0.003738, "danceability": 0.586686, "instrumentalness": 0.0, "key": 5, "duration": 247.90354, "loudness": -15.652, "audio_md5": "3c717d60c9598ca52a639c5f630df0d2", "valence": 0.640939, "mode": 1}}, {"song_hotttnesss": 0.0, "title": "Behind The Scenes of Little Secrets", "artist_discovery": 0.3739098292227674, "artist_name": "Passion Pit", "song_type": ["electric", "vocal"], "artist_hotttnesss": 0.627164, "artist_location": {"latitude": 42.3668, "location": "Cambridge, MA, US", "longitude": -71.106}, "song_currency": 0.0, "artist_familiarity": 0.700862, "artist_id": "AR6PFD411C8A416424", "id": "SOUQRRM13E907F2768", "audio_summary": {"time_signature": 4, "analysis_url": "http://echonest-analysis.s3.amazonaws.com/TR/wFRQ9wJvOYV0S7ACdJ_JSBpfp1cxlYtPJAPJVb/3/full.json?AWSAccessKeyId=AKIAJRDFEY23UEVW42BQ&Expires=1445727099&Signature=H/o1YO/lNxqu5EdFTy%2BsaxEwgyg%3D", "energy": 0.548563, "liveness": 0.802617, "tempo": 99.402, "speechiness": 0.250848, "acousticness": 0.177171, "danceability": 0.493826, "instrumentalness": 0.0, "key": 10, "duration": 247.13556, "loudness": -17.174, "audio_md5": "057af869477edff1f4e527eea250962e", "valence": 0.620402, "mode": 0}}, {"song_hotttnesss": 0.0, "title": "Little Secrets (Live on Letterman)", "artist_discovery": 0.3739098292227674, "artist_name": "Passion Pit", "song_type": ["live", "electric", "vocal"], "artist_hotttnesss": 0.627164, "artist_location": {"latitude": 42.3668, "location": "Cambridge, MA, US", "longitude": -71.106}, "song_currency": 0.0, "artist_familiarity": 0.700862, "artist_id": "AR6PFD411C8A416424", "id": "SOLZDTZ143F55944C6", "audio_summary": {"time_signature": 4, "analysis_url": "http://echonest-analysis.s3.amazonaws.com/TR/MI9s6A91CY4dcJri40mQKt9WWXUNqX7meCwdi4/3/full.json?AWSAccessKeyId=AKIAJRDFEY23UEVW42BQ&Expires=1445727099&Signature=sKVtm38aA6lJvehdAlTCwwHAs3k%3D", "energy": 0.548854, "liveness": 0.963772, "tempo": 106.005, "speechiness": 0.043001, "acousticness": 0.031763, "danceability": 0.5028, "instrumentalness": 0.0, "key": 0, "duration": 252.64, "loudness": -18.803, "audio_md5": "f4409e5e15da574ac962a2298085bcf8", "valence": 0.675297, "mode": 1}}, {"song_hotttnesss": 0.114513, "title": "Little Secrets (Jack Beats Remix)", "artist_discovery": 0.3739098292227674, "artist_name": "Passion Pit", "song_type": ["remix", "studio", "electric", "vocal"], "artist_hotttnesss": 0.627164, "artist_location": {"latitude": 42.3668, "location": "Cambridge, MA, US", "longitude": -71.106}, "song_currency": 7.668711656441718e-05, "artist_familiarity": 0.700862, "artist_id": "AR6PFD411C8A416424", "id": "SOEUWDQ12AC468833F", "audio_summary": {"time_signature": 4, "analysis_url": "http://echonest-analysis.s3.amazonaws.com/TR/_01e5wt33lCxycJ_u5L73w9o4-b7YyICG5V2ET/3/full.json?AWSAccessKeyId=AKIAJRDFEY23UEVW42BQ&Expires=1445727099&Signature=K8PeOusFSwSvbwtll2uyyN5i9%2BY%3D", "energy": 0.844376, "liveness": 0.448792, "tempo": 130.042, "speechiness": 0.049435, "acousticness": 0.000534, "danceability": 0.678895, "instrumentalness": 0.100355, "key": 9, "duration": 277.99982, "loudness": -7.66, "audio_md5": "716070920421d8af1ea8e594dbeaf265", "valence": 0.22798, "mode": 1}}, {"song_hotttnesss": 0.14716, "song_currency_rank": 1846941, "artist_discovery_rank": 189188, "title": "More Little Secrets (Original Mix)", "artist_discovery": 0.3739098292227674, "song_hotttnesss_rank": 1023816, "artist_name": "Passion Pit", "song_type": ["studio", "electric", "vocal"], "artist_hotttnesss": 0.627164, "artist_familiarity_rank": 747, "artist_location": {"latitude": 42.3668, "location": "Cambridge, MA, US", "longitude": -71.106}, "song_currency": 0.00026298701298701295, "id": "SOEAHTI1315CD4D378", "artist_familiarity": 0.700862, "artist_id": "AR6PFD411C8A416424", "artist_hotttnesss_rank": 3575, "audio_summary": {"time_signature": 4, "analysis_url": "http://echonest-analysis.s3.amazonaws.com/TR/7842RwgH7B4TSavOa4L8qHZzk1HjJTTshh4vp5NKPoE-aRY4RKX1CHAhSIE-DTh5D4_DUINt9NYwHVprQ%3D/3/full.json?AWSAccessKeyId=AKIAJRDFEY23UEVW42BQ&Expires=1445727099&Signature=QCMlRTA1BHXBTIoP4zl4nLi0G98%3D", "energy": 0.748199, "liveness": 0.445767, "tempo": 129.93, "speechiness": 0.068695, "acousticness": 0.000482, "danceability": 0.919276, "instrumentalness": 0.048607, "key": 0, "duration": 315.71356, "loudness": -7.739, "audio_md5": "", "valence": 0.220886, "mode": 1}}, {"song_hotttnesss": 0.088599, "title": "Little Secrets (Hey Champ Remix)", "artist_discovery": 0.3739098292227674, "artist_name": "Passion Pit", "song_type": ["remix", "studio", "electric", "vocal"], "artist_hotttnesss": 0.627164, "artist_location": {"latitude": 42.3668, "location": "Cambridge, MA, US", "longitude": -71.106}, "song_currency": 7.142857142857143e-05, "artist_familiarity": 0.700862, "artist_id": "AR6PFD411C8A416424", "id": "SOPALAH12AB018377A", "audio_summary": {"time_signature": 4, "analysis_url": "http://echonest-analysis.s3.amazonaws.com/TR/ygdHYABg-xF6oc6x-jEcvFNyZb6AoTsTxixIjr0wwg17V6OgmDmsZA-I-8wa84nFBR3MgFqFtD31gwwco%3D/3/full.json?AWSAccessKeyId=AKIAJRDFEY23UEVW42BQ&Expires=1445727099&Signature=oQkCES1BpAGG4SMYxvea4j1fstc%3D", "energy": 0.553963, "liveness": 0.058376, "tempo": 120.617, "speechiness": 0.124428, "acousticness": 0.005861, "danceability": 0.787252, "instrumentalness": 0.161893, "key": 10, "duration": 270.17288, "loudness": -7.478, "audio_md5": "1957bb8dfc4dec0a6decf88e0d84e547", "valence": 0.723996, "mode": 1}}, {"song_hotttnesss": 0.114513, "song_currency_rank": 4622251, "artist_discovery_rank": 189188, "title": "Little Secrets (Jack Beats Remix)", "artist_discovery": 0.3739098292227674, "song_hotttnesss_rank": 1482503, "artist_name": "Passion Pit", "song_type": ["remix", "studio", "electric", "vocal"], "artist_hotttnesss": 0.627164, "artist_familiarity_rank": 747, "artist_location": {"latitude": 42.3668, "location": "Cambridge, MA, US", "longitude": -71.106}, "song_currency": 7.668711656441718e-05, "id": "SOZXCJN1461B15AA11", "artist_familiarity": 0.700862, "artist_id": "AR6PFD411C8A416424", "artist_hotttnesss_rank": 3575, "audio_summary": {"time_signature": 4, "analysis_url": "http://echonest-analysis.s3.amazonaws.com/TR/YjGXow4yiB5rwFRX1w93eslsC7E-yJva5-pTtu2MoTCgGQ5aU6lGjyF0bFauLFFXwxL037V2bs0WY3utY%3D/3/full.json?AWSAccessKeyId=AKIAJRDFEY23UEVW42BQ&Expires=1445727099&Signature=PL%2BQoKWJHzBXYo%2BONeuehHiuPV8%3D", "energy": 0.858447, "liveness": 0.205621, "tempo": 128.979, "speechiness": 0.045913, "acousticness": 0.000662, "danceability": 0.678931, "instrumentalness": 0.129302, "key": 9, "duration": 277.16, "loudness": -5.062, "audio_md5": "", "valence": 0.198338, "mode": 1}}, {"song_hotttnesss": 0.0, "title": "Little Secrets (Live in Central Park)", "artist_discovery": 0.3739098292227674, "artist_name": "Passion Pit", "song_type": ["electric", "vocal"], "artist_hotttnesss": 0.627164, "artist_location": {"latitude": 42.3668, "location": "Cambridge, MA, US", "longitude": -71.106}, "song_currency": 0.0, "artist_familiarity": 0.700862, "artist_id": "AR6PFD411C8A416424", "id": "SORNQGE13E907F1F06", "audio_summary": {"time_signature": 4, "analysis_url": "http://echonest-analysis.s3.amazonaws.com/TR/36ZipQrXK53YxYAuE-tn61JqZup_r09iI1ai6W/3/full.json?AWSAccessKeyId=AKIAJRDFEY23UEVW42BQ&Expires=1445727099&Signature=aWexYTUn87Zc4fG68kb%2BaAhCSSI%3D", "energy": 0.788648, "liveness": 0.880862, "tempo": 105.994, "speechiness": 0.068901, "acousticness": 0.023635, "danceability": 0.54347, "instrumentalness": 0.0, "key": 0, "duration": 264.09556, "loudness": -7.986, "audio_md5": "0dc7f1471ee2b057a2f86bd134cefe03", "valence": 0.48096, "mode": 1}}, {"song_hotttnesss": 0.0, "title": "LITTLE SECRETS (Radio Edit)/(CC Cleaner)/(LYRICS!)", "artist_discovery": 0.3739098292227674, "artist_name": "Passion Pit", "song_type": ["studio", "electric", "vocal"], "artist_hotttnesss": 0.627164, "artist_location": {"latitude": 42.3668, "location": "Cambridge, MA, US", "longitude": -71.106}, "song_currency": 0.0, "artist_familiarity": 0.700862, "artist_id": "AR6PFD411C8A416424", "id": "SONZACN13732E82AEF", "audio_summary": {"time_signature": 4, "analysis_url": "http://echonest-analysis.s3.amazonaws.com/TR/TRSAQZM12BF998A910/3/full.json?AWSAccessKeyId=AKIAJRDFEY23UEVW42BQ&Expires=1445727099&Signature=%2B7oYt93s%2BuuRif4653GLJg/Q%2BVQ%3D", "energy": 0.373064, "liveness": 0.186876, "tempo": 99.94, "speechiness": 0.037301, "acousticness": 0.018426, "danceability": 0.608816, "instrumentalness": 0.003268, "key": 4, "duration": 209.05751, "loudness": -18.584, "audio_md5": "45ae360b5c927e4c693b5fc61c38910d", "valence": 0.566927, "mode": 0}}, {"song_hotttnesss": 0.0, "title": "Little Secrets (Live in Central Park)", "artist_discovery": 0.3739098292227674, "artist_name": "Passion Pit", "song_type": ["electric", "vocal"], "artist_hotttnesss": 0.627164, "artist_location": {"latitude": 42.3668, "location": "Cambridge, MA, US", "longitude": -71.106}, "song_currency": 0.0, "artist_familiarity": 0.700862, "artist_id": "AR6PFD411C8A416424", "id": "SOAGDDA13E907F1AEC", "audio_summary": {"time_signature": 4, "analysis_url": "http://echonest-analysis.s3.amazonaws.com/TR/TeQk0QZHcO_6rLG1JRzhSvSHOoNdGjUnbuvcUj/3/full.json?AWSAccessKeyId=AKIAJRDFEY23UEVW42BQ&Expires=1445727099&Signature=fjN%2BgElf73BGTppZ13qYZQk4i0E%3D", "energy": 0.760296, "liveness": 0.827186, "tempo": 105.859, "speechiness": 0.076966, "acousticness": 0.020629, "danceability": 0.492877, "instrumentalness": 1e-06, "key": 0, "duration": 279.13556, "loudness": -9.021, "audio_md5": "b0730f898a852fd0c32273c9367d7a60", "valence": 0.482245, "mode": 1}}, {"song_hotttnesss": 0.0, "title": "Little Secrets (Felix Da Housecat Pink Enemy Remix)", "artist_discovery": 0.3739098292227674, "artist_name": "Passion Pit", "song_type": ["remix", "studio", "electric", "vocal"], "artist_hotttnesss": 0.627164, "artist_location": {"latitude": 42.3668, "location": "Cambridge, MA, US", "longitude": -71.106}, "song_currency": 0.0, "artist_familiarity": 0.700862, "artist_id": "AR6PFD411C8A416424", "id": "SOXKOIA146208B8883", "audio_summary": {"time_signature": 4, "analysis_url": "http://echonest-analysis.s3.amazonaws.com/TR/9n8Iqgn6NNEE_ozWP_lqejBJOFhqNL_ZkYCJLcrCO4r4BsK0CwiSUXDCW0lJYqGuO3pXGk5uzTlKLau4I%3D/3/full.json?AWSAccessKeyId=AKIAJRDFEY23UEVW42BQ&Expires=1445727099&Signature=m5zltXbP%2BvHJIREhnBEogaznfdg%3D", "energy": 0.754705, "liveness": 0.102924, "tempo": 120.025, "speechiness": 0.050976, "acousticness": 0.021157, "danceability": 0.548786, "instrumentalness": 0.016021, "key": 5, "duration": 313.25333, "loudness": -8.391, "audio_md5": "", "valence": 0.302779, "mode": 1}}, {"song_hotttnesss": 0.0, "title": "Little Secrets - Felix Da Housecat Pink Enemy Remix", "artist_discovery": 0.3739098292227674, "artist_name": "Passion Pit", "song_type": ["remix", "studio", "electric", "vocal"], "artist_hotttnesss": 0.627164, "artist_location": {"latitude": 42.3668, "location": "Cambridge, MA, US", "longitude": -71.106}, "song_currency": 0.051535573537299165, "artist_familiarity": 0.700862, "artist_id": "AR6PFD411C8A416424", "id": "SOJHCOQ13FD2E55266", "audio_summary": {"time_signature": 4, "analysis_url": "http://echonest-analysis.s3.amazonaws.com/TR/hq0QkQfaT6AP-1SaQa5cxJnE7xmKTBfBlxuxQ52iyeoJMSZ62QrYHfy8QiEqavmIpQ6bf1Sx5Vzab01qw%3D/3/full.json?AWSAccessKeyId=AKIAJRDFEY23UEVW42BQ&Expires=1445727099&Signature=N3eDjtAy7ERnG5ibKdf5lzYTxqM%3D", "energy": 0.867258, "liveness": 0.594179, "tempo": 127.956, "speechiness": 0.0779, "acousticness": 0.094844, "danceability": 0.470795, "instrumentalness": 0.105045, "key": 5, "duration": 240.06667, "loudness": -7.232, "audio_md5": "", "valence": 0.301917, "mode": 1}}]}}