{"response": {"status": {"code": 0, "message": "Success", "version": "4.2"}, "songs": [{"song_hotttnesss": 0.461647, "song_currency_rank": 14951, "artist_discovery_rank": 253698, "title": "Spies", "artist_discovery": 0.3491834632617394, "song_hotttnesss_rank": 10183, "artist_name": "Coldplay", "song_type": ["studio", "electric", "vocal"], "artist_hotttnesss": 0.894171, "artist_familiarity_rank": 24, "artist_location": {"latitude": 51.5072648, "location": "London, England", "longitude": -0.1278328}, "song_currency": 0.04752482121780185, "id": "SOTRQEJ12AF72A45D7", "artist_familiarity": 0.85856, "artist_id": "ARJ7KF01187B98D717", "artist_hotttnesss_rank": 56, "audio_summary": {"time_signature": 4, "analysis_url": "http://echonest-analysis.s3.amazonaws.com/TR/3ais8AEQ5uWhM00c5w2H15L_rljkQSLI4JAfy4BDlnMGQ9DL0E6D6MIJsI8tnJ6IYnVwwIgPAcAE0yw3s%3D/3/full.json?AWSAccessKeyId=AKIAJRDFEY23UEVW42BQ&Expires=1445742063&Signature=EpO7hA/7hQ4r5hU/Bpjh7hM2fg0%3D", "energy": 0.674452, "liveness": 0.063495, "tempo": 147.607, "speechiness": 0.032022, "acousticness": 0.023405, "danceability": 0.309165, "instrumentalness": 0.000155, "key": 1, "duration": 318.77333, "loudness": -5.527, "audio_md5": "", "valence": 0.072068, "mode": 0}}, {"song_hotttnesss": 0.0, "artist_discovery_rank": 253698, "title": "Spies (Live)", "artist_discovery": 0.3491834632617394, "artist_hotttnesss_rank": 56, "artist_name": "Coldplay", "song_type": ["live", "electric", "vocal"], "artist_hotttnesss": 0.894171, "artist_familiarity_rank": 24, "artist_location": {"latitude": 51.5072648, "location": "London, England", "longitude": -0.1278328}, "song_currency": 0.0, "artist_familiarity": 0.85856, "artist_id": "ARJ7KF01187B98D717", "id": "SOGQWFS14A80D4A96C", "audio_summary": {"time_signature": 3, "analysis_url": "http://echonest-analysis.s3.amazonaws.com/TR/dyMlpwrt2c000jq_9MzFAYO0YevLODt0eg9MDttmzu4m7Q3sPd4gcPj091m4NGF5AHfyXDDJO5aKMDyVU%3D/3/full.json?AWSAccessKeyId=AKIAJRDFEY23UEVW42BQ&Expires=1445742063&Signature=Ov8YJeJKMNB9OV8NDLFf3gYrqig%3D", "energy": 0.758293, "liveness": 0.948922, "tempo": 135.038, "speechiness": 0.051841, "acousticness": 0.31768, "danceability": 0.261361, "instrumentalness": 0.029273, "key": 1, "duration": 331.34259, "loudness": -8.032, "audio_md5": "", "valence": 0.322764, "mode": 0}}]}}