{"response": {"status": {"code": 0, "message": "Success", "version": "4.2"}, "songs": [{"song_hotttnesss": 0.347639, "song_currency_rank": 154899, "artist_discovery_rank": 2691, "title": "Marienbad", "artist_discovery": 0.5583107746967196, "song_hotttnesss_rank": 76758, "artist_name": "Julia Holter", "song_type": ["studio", "vocal"], "artist_hotttnesss": 0.728541, "artist_familiarity_rank": 5531, "artist_location": {"latitude": 33.973951, "location": "Los Angeles, CA", "longitude": -118.248405}, "song_currency": 0.0037253808992939426, "id": "SOETUZE13AF27BE595", "artist_familiarity": 0.555838, "artist_id": "AREUWSB1269FB35304", "artist_hotttnesss_rank": 1114, "audio_summary": {"time_signature": 4, "analysis_url": "http://echonest-analysis.s3.amazonaws.com/TR/kZ3uEAJB3KeEeXCQ_H_wOAc-977wN7_5EJ0PTdkPR9agy2Wh33Hz4Smq83QXbCTFwYfefadzg8EZDsS-4%3D/3/full.json?AWSAccessKeyId=AKIAJRDFEY23UEVW42BQ&Expires=1445728252&Signature=E0G7hVP3RHNoZlo%2BMUpAnQyppfI%3D", "energy": 0.36702, "liveness": 0.10641, "tempo": 107.724, "speechiness": 0.047611, "acousticness": 0.750265, "danceability": 0.449414, "instrumentalness": 0.000238, "key": 11, "duration": 324.81333, "loudness": -9.66, "audio_md5": "", "valence": 0.177235, "mode": 1}}, {"song_hotttnesss": 0.0, "title": "Marienbad (Live)", "artist_discovery": 0.5583107746967196, "artist_name": "Julia Holter", "song_type": ["acoustic", "studio"], "artist_hotttnesss": 0.728541, "artist_location": {"latitude": 33.973951, "location": "Los Angeles, CA", "longitude": -118.248405}, "song_currency": 0.0, "artist_familiarity": 0.555838, "artist_id": "AREUWSB1269FB35304", "id": "SOTQANM13EA80203A9", "audio_summary": {"time_signature": 4, "analysis_url": "http://echonest-analysis.s3.amazonaws.com/TR/NTJagwO_zcCEAgntPXWB4zuZi9rSTwj9B14CVL/3/full.json?AWSAccessKeyId=AKIAJRDFEY23UEVW42BQ&Expires=1445728252&Signature=vTqMe8C2Vgso3Ug1m7hcQ4iTq9k%3D", "energy": 0.185837, "liveness": 0.091628, "tempo": 89.749, "speechiness": 0.033031, "acousticness": 0.978693, "danceability": 0.230946, "instrumentalness": 0.658691, "key": 1, "duration": 255.7268, "loudness": -13.9, "audio_md5": "fe559e727e750520d83c8c78c9e60101", "valence": 0.037006, "mode": 0}}]}}