{"response": {"status": {"code": 0, "message": "Success", "version": "4.2"}, "songs": [{"song_hotttnesss": 0.0, "title": "\u042f\u0439\u0446\u0430 \u0424\u0430\u0431\u0435\u0440\u0436\u0435", "artist_discovery": 0.4611315611710863, "artist_name": "\u041d\u043e\u0433\u0443 \u0421\u0432\u0435\u043b\u043e!", "song_type": ["studio", "electric", "vocal"], "artist_hotttnesss": 0.481735, "artist_location": {}, "song_currency": 0.001607142857142857, "artist_familiarity": 0.294915, "artist_id": "ARUEUXF13559202D52", "id": "SOVMERX14508946424", "audio_summary": {"time_signature": 4, "analysis_url": "http://echonest-analysis.s3.amazonaws.com/TR/wSLhpwZk4kfSmQX50fbevTVs5KSorlpu0-FEgD37mCLpRT2_FJg3tNdnSXgTNEqq7jLP-IoRAiA3RRte0%3D/3/full.json?AWSAccessKeyId=AKIAJRDFEY23UEVW42BQ&Expires=1445740434&Signature=cyeuillOucXUfzmAI7h8/z2P9K0%3D", "energy": 0.914784, "liveness": 0.333902, "tempo": 95.115, "speechiness": 0.081834, "acousticness": 0.002587, "danceability": 0.582429, "instrumentalness": 0.02471, "key": 7, "duration": 188.9727, "loudness": -4.158, "audio_md5": "", "valence": 0.641301, "mode": 1}}]}}