{"response": {"status": {"code": 0, "message": "Success", "version": "4.2"}, "songs": [{"song_hotttnesss": 0.070213, "title": "Be Kind, Don't Rewind", "artist_discovery": 0.516513006975436, "artist_name": "Fauve", "song_type": ["studio", "vocal"], "artist_hotttnesss": 0.622374, "artist_location": {"latitude": 48.866667, "location": "Paris, France", "longitude": 2.333333}, "song_currency": 4.545454545454546e-05, "artist_familiarity": 0.502205, "artist_id": "ARKXPUR12D5CD729E0", "id": "SOILYPW13660C08F0A", "audio_summary": {"time_signature": 4, "analysis_url": "http://echonest-analysis.s3.amazonaws.com/TR/T-8YlgR9dpdML_8J0nWg103hqGZq-zSI-JLBQ9eosI4wgILRxUtPWCWaVzz2iSmnVT2Wml1KM7LB_1Z7Q%3D/3/full.json?AWSAccessKeyId=AKIAJRDFEY23UEVW42BQ&Expires=1445737536&Signature=%2BFVTIHo571q3edZPRysOC0Km5qE%3D", "energy": 0.607832, "liveness": 0.673199, "tempo": 131.914, "speechiness": 0.043325, "acousticness": 0.476664, "danceability": 0.513707, "instrumentalness": 0.143099, "key": 8, "duration": 260.57333, "loudness": -9.993, "audio_md5": "", "valence": 0.361748, "mode": 1}}, {"song_hotttnesss": 0.070213, "title": "Be Kind, Don't Rewind", "artist_discovery": 0.516513006975436, "artist_name": "Fauve", "song_type": ["studio", "vocal"], "artist_hotttnesss": 0.622374, "artist_location": {"latitude": 48.866667, "location": "Paris, France", "longitude": 2.333333}, "song_currency": 4.545454545454546e-05, "artist_familiarity": 0.502205, "artist_id": "ARKXPUR12D5CD729E0", "id": "SONAABQ13FC6230091", "audio_summary": {"time_signature": 4, "analysis_url": "http://echonest-analysis.s3.amazonaws.com/TR/kIq6WwCMeKwsAmP_vy1fg1Rh-R0ZO58H7bMLNhdcYCyr3I1Z9GOPoy2qCIQ787YfQi211CnFBj_Nbh0TQ%3D/3/full.json?AWSAccessKeyId=AKIAJRDFEY23UEVW42BQ&Expires=1445737536&Signature=YVFGTk7A2QgyGETxCQ4kQa8Ffmk%3D", "energy": 0.608066, "liveness": 0.467687, "tempo": 131.97, "speechiness": 0.046148, "acousticness": 0.487167, "danceability": 0.56181, "instrumentalness": 0.153699, "key": 8, "duration": 252.55955, "loudness": -9.835, "audio_md5": "f843da89334abf9145740245ecac64a5", "valence": 0.34619, "mode": 1}}]}}