{"response": {"status": {"code": 0, "message": "Success", "version": "4.2"}, "songs": [{"song_hotttnesss": 0.227226, "title": "We Are Together", "artist_discovery": 0.492388974476079, "artist_name": "Planet Of Sound", "song_type": ["studio", "electric"], "artist_hotttnesss": 0.514389, "artist_location": {"latitude": 51.5072648, "location": "London", "longitude": -0.1278328}, "song_currency": 0.0008038942976356051, "artist_familiarity": 0.333326, "artist_id": "ARVZXCI145701FAE8B", "id": "SOBTACB14AD2468AF0", "audio_summary": {"time_signature": 4, "analysis_url": "http://echonest-analysis.s3.amazonaws.com/TR/p38dUgLG9rpa0uTfW6yG3KTxW4W23A_nmjIXbgT2xU8hg9d89qYIa59zAZN7lNgn18TIOadSqYukHMBJI%3D/3/full.json?AWSAccessKeyId=AKIAJRDFEY23UEVW42BQ&Expires=1445732751&Signature=h/rVOZqUqHTBMljZ58L1FK%2BvBxA%3D", "energy": 0.693607, "liveness": 0.35346, "tempo": 120.998, "speechiness": 0.081801, "acousticness": 0.064934, "danceability": 0.533285, "instrumentalness": 0.735582, "key": 3, "duration": 194.37973, "loudness": -8.832, "audio_md5": "0707515fba6aad1444947cd19c66d8e9", "valence": 0.179344, "mode": 1}}, {"song_hotttnesss": 0.227226, "title": "We Are Together", "artist_discovery": 0.492388974476079, "artist_name": "Planet Of Sound", "song_type": ["electric"], "artist_hotttnesss": 0.514389, "artist_location": {"latitude": 51.5072648, "location": "London", "longitude": -0.1278328}, "song_currency": 0.0008038942976356051, "artist_familiarity": 0.333326, "artist_id": "ARVZXCI145701FAE8B", "id": "SOXNVGQ146F7AB0238", "audio_summary": {"time_signature": 4, "analysis_url": "http://echonest-analysis.s3.amazonaws.com/TR/UiOooQrlNp_INCVYfclkdotd6ufK_8v4rnM9hrX1D630eJv7t-1xLilghGomqIfAl58d5aKdS1LwCZPgY%3D/3/full.json?AWSAccessKeyId=AKIAJRDFEY23UEVW42BQ&Expires=1445732751&Signature=mv22EoN6LfFv8Di8fiK5%2BijI/FM%3D", "energy": 0.737265, "liveness": 0.80413, "tempo": 116.963, "speechiness": 0.035041, "acousticness": 0.010806, "danceability": 0.546493, "instrumentalness": 0.730332, "key": 0, "duration": 157.90621, "loudness": -8.268, "audio_md5": "cd2dac0317f664ddbcc4e833b2d9a754", "valence": 0.411906, "mode": 0}}, {"song_hotttnesss": 0.227226, "title": "We Are Together", "artist_discovery": 0.492388974476079, "artist_name": "Planet Of Sound", "song_type": ["studio", "electric", "vocal"], "artist_hotttnesss": 0.514389, "artist_location": {"latitude": 51.5072648, "location": "London", "longitude": -0.1278328}, "song_currency": 0.0008038942976356051, "artist_familiarity": 0.333326, "artist_id": "ARVZXCI145701FAE8B", "id": "SOAIFFC147F608511A", "audio_summary": {"time_signature": 4, "analysis_url": "http://echonest-analysis.s3.amazonaws.com/TR/Q_eDgghjzYq58InavcLJcM4WSnwDyRp1nua7NGgBdqnvaosqZhfIBuFf2ZVc0k-spskzOYwaxeu_hV0Gs%3D/3/full.json?AWSAccessKeyId=AKIAJRDFEY23UEVW42BQ&Expires=1445732751&Signature=DnW3U2w6/9fIJYJiZeUvEIAM234%3D", "energy": 0.813189, "liveness": 0.244425, "tempo": 116.963, "speechiness": 0.03833, "acousticness": 0.090752, "danceability": 0.487572, "instrumentalness": 3e-06, "key": 3, "duration": 184.56626, "loudness": -4.636, "audio_md5": "9d64c453493ed8286fab72eb1a5d63c5", "valence": 0.447808, "mode": 1}}, {"song_hotttnesss": 0.227226, "title": "We Are Together", "artist_discovery": 0.492388974476079, "artist_name": "Planet Of Sound", "song_type": ["studio", "electric"], "artist_hotttnesss": 0.514389, "artist_location": {"latitude": 51.5072648, "location": "London", "longitude": -0.1278328}, "song_currency": 0.0008038942976356051, "artist_familiarity": 0.333326, "artist_id": "ARVZXCI145701FAE8B", "id": "SOMBPWQ14577307059", "audio_summary": {"time_signature": 4, "analysis_url": "http://echonest-analysis.s3.amazonaws.com/TR/kt0IDAg3Vs2pI6MyFfphItkA4D6ksn0NZiCbyInCxEWhEkhB1hD5jBea-7ALbhq0mHeWx7aW1y2_G5Vk0%3D/3/full.json?AWSAccessKeyId=AKIAJRDFEY23UEVW42BQ&Expires=1445732751&Signature=BGZbcP2/7eaQauBrq8uQ6a6smeg%3D", "energy": 0.906333, "liveness": 0.520095, "tempo": 119.998, "speechiness": 0.041991, "acousticness": 3.2e-05, "danceability": 0.620428, "instrumentalness": 0.861033, "key": 0, "duration": 183.99565, "loudness": -8.147, "audio_md5": "7de279dca47399a418ec0845da011867", "valence": 0.272672, "mode": 0}}, {"song_hotttnesss": 0.227226, "title": "We Are Together", "artist_discovery": 0.492388974476079, "artist_name": "Planet Of Sound", "song_type": ["studio", "electric"], "artist_hotttnesss": 0.514389, "artist_location": {"latitude": 51.5072648, "location": "London", "longitude": -0.1278328}, "song_currency": 0.0008038942976356051, "artist_familiarity": 0.333326, "artist_id": "ARVZXCI145701FAE8B", "id": "SORRCLO14577305AB0", "audio_summary": {"time_signature": 4, "analysis_url": "http://echonest-analysis.s3.amazonaws.com/TR/De6i1Avwd3X5PT4cJFgXWOSKCVNZEaBDCm8r7AAPxJOdDM-KHFqSQmapKoG8E_7QhRPhZ3EhlkEexc20E%3D/3/full.json?AWSAccessKeyId=AKIAJRDFEY23UEVW42BQ&Expires=1445732751&Signature=yEnpZJg1bxdwPPSwxOny9c6chOQ%3D", "energy": 0.674297, "liveness": 0.161498, "tempo": 116.994, "speechiness": 0.057821, "acousticness": 0.037924, "danceability": 0.721701, "instrumentalness": 0.830901, "key": 3, "duration": 240.51238, "loudness": -12.21, "audio_md5": "935ccad66cd94c928babc3cdccce724f", "valence": 0.501705, "mode": 1}}, {"song_hotttnesss": 0.227226, "song_currency_rank": 626337, "artist_discovery_rank": 14550, "title": "We Are Together", "artist_discovery": 0.492388974476079, "song_hotttnesss_rank": 404334, "artist_name": "Planet Of Sound", "song_type": ["studio", "electric"], "artist_hotttnesss": 0.514389, "artist_familiarity_rank": 99724, "artist_location": {"latitude": 51.5072648, "location": "London", "longitude": -0.1278328}, "song_currency": 0.0008038942976356051, "id": "SOPKDNB14577304366", "artist_familiarity": 0.333326, "artist_id": "ARVZXCI145701FAE8B", "artist_hotttnesss_rank": 26844, "audio_summary": {"time_signature": 4, "analysis_url": "http://echonest-analysis.s3.amazonaws.com/TR/0U13SwtfgvCQ2MwX1f-wcDncqf9H_6T6PEyqPp_88XNKaEOdDFY2p0vafOQYc1XsZ5iXxH6iuDyARuNjE%3D/3/full.json?AWSAccessKeyId=AKIAJRDFEY23UEVW42BQ&Expires=1445732751&Signature=FZFKtPUqRVf5%2Bn7yLyRPpS0l4/U%3D", "energy": 0.767635, "liveness": 0.228525, "tempo": 116.975, "speechiness": 0.034402, "acousticness": 0.013987, "danceability": 0.540778, "instrumentalness": 0.476155, "key": 0, "duration": 169.68, "loudness": -6.352, "audio_md5": "", "valence": 0.373735, "mode": 0}}, {"song_hotttnesss": 0.227226, "title": "We Are Together", "artist_discovery": 0.492388974476079, "artist_name": "Planet Of Sound", "song_type": ["studio", "electric"], "artist_hotttnesss": 0.514389, "artist_location": {"latitude": 51.5072648, "location": "London", "longitude": -0.1278328}, "song_currency": 0.0008038942976356051, "artist_familiarity": 0.333326, "artist_id": "ARVZXCI145701FAE8B", "id": "SOKJIXH14577309812", "audio_summary": {"time_signature": 4, "analysis_url": "http://echonest-analysis.s3.amazonaws.com/TR/CNqFIwtx2mYRnPvOZYMMR6TGOE0PDDvuxSprkOxOw4dg7dXVGFP4kPBuZEfNp546rsi-XI4xksRSAERmE%3D/3/full.json?AWSAccessKeyId=AKIAJRDFEY23UEVW42BQ&Expires=1445732751&Signature=/T5gcuOjEylm8Q69jUHp2mCKsW4%3D", "energy": 0.740323, "liveness": 0.125039, "tempo": 121.031, "speechiness": 0.064435, "acousticness": 0.009821, "danceability": 0.803307, "instrumentalness": 0.851368, "key": 3, "duration": 183.23007, "loudness": -6.432, "audio_md5": "2a91f703638febe4eef740363f02954f", "valence": 0.902606, "mode": 0}}, {"song_hotttnesss": 0.0, "title": "We Are Together - Radio Edit", "artist_discovery": 0.492388974476079, "artist_name": "Planet Of Sound", "song_type": ["electric"], "artist_hotttnesss": 0.514389, "artist_location": {"latitude": 51.5072648, "location": "London", "longitude": -0.1278328}, "song_currency": 0.0, "artist_familiarity": 0.333326, "artist_id": "ARVZXCI145701FAE8B", "id": "SOHPJJF14FAE564FEE", "audio_summary": {"time_signature": 4, "analysis_url": "http://echonest-analysis.s3.amazonaws.com/TR/_4uDagzMkneko8Aeoy2UgT8xLr_K1gD-6IwfeY2mM1lX9q4GT-wfuRzB6-6Z40zVYxZ0t-3rNOEnbrtO4%3D/3/full.json?AWSAccessKeyId=AKIAJRDFEY23UEVW42BQ&Expires=1445732751&Signature=YJ59SqCcsjGtuoBEaF8BCZD%2BI6g%3D", "energy": 0.748044, "liveness": 0.79943, "tempo": 117.033, "speechiness": 0.034958, "acousticness": 0.012043, "danceability": 0.537245, "instrumentalness": 0.665563, "key": 8, "duration": 157.90667, "loudness": -8.226, "audio_md5": "", "valence": 0.45098, "mode": 1}}, {"song_hotttnesss": 0.158813, "song_currency_rank": 1590313, "artist_discovery_rank": 14550, "title": "We Are Together (Original Mix)", "artist_discovery": 0.492388974476079, "song_hotttnesss_rank": 897893, "artist_name": "Planet Of Sound", "song_type": ["studio", "electric"], "artist_hotttnesss": 0.514389, "artist_familiarity_rank": 99724, "artist_location": {"latitude": 51.5072648, "location": "London", "longitude": -0.1278328}, "song_currency": 0.00037345679012345677, "id": "SOKXYZT14577304EBB", "artist_familiarity": 0.333326, "artist_id": "ARVZXCI145701FAE8B", "artist_hotttnesss_rank": 26844, "audio_summary": {"time_signature": 4, "analysis_url": "http://echonest-analysis.s3.amazonaws.com/TR/sSuWSg5fce9JLaD9X3Fn4VtRx__f5PhYvYJZMkG59NKlO4RpYrSydX4CVUvbNwknwarGH7pazKEE4Cz8s%3D/3/full.json?AWSAccessKeyId=AKIAJRDFEY23UEVW42BQ&Expires=1445732751&Signature=8eCRF7nNwuQHkYKgEG/TQL3wd/4%3D", "energy": 0.795565, "liveness": 0.233391, "tempo": 116.969, "speechiness": 0.03162, "acousticness": 0.013455, "danceability": 0.540273, "instrumentalness": 0.6613, "key": 8, "duration": 386.38032, "loudness": -6.847, "audio_md5": "98827c8243348554eef44a969a00470c", "valence": 0.331921, "mode": 1}}, {"song_hotttnesss": 0.184726, "song_currency_rank": 1478764, "artist_discovery_rank": 14550, "title": "We Are Together (Radio Edit)", "artist_discovery": 0.492388974476079, "song_hotttnesss_rank": 665955, "artist_name": "Planet Of Sound", "song_type": ["studio", "electric"], "artist_hotttnesss": 0.514389, "artist_familiarity_rank": 99724, "artist_location": {"latitude": 51.5072648, "location": "London", "longitude": -0.1278328}, "song_currency": 0.00044461538461538466, "id": "SOUAIWS145B4446D50", "artist_familiarity": 0.333326, "artist_id": "ARVZXCI145701FAE8B", "artist_hotttnesss_rank": 26844, "audio_summary": {"time_signature": 4, "analysis_url": "http://echonest-analysis.s3.amazonaws.com/TR/piqS5A0sr3OHauU4A51KskSpBShNZZVaTzg7L5abGdXO5lJuT0mzRBPm_g7phnwIu9ur2bNLJNN2Zn1tI%3D/3/full.json?AWSAccessKeyId=AKIAJRDFEY23UEVW42BQ&Expires=1445732751&Signature=a6PfIpfaufHE0qn8Dxjjsro6qEg%3D", "energy": 0.775982, "liveness": 0.232208, "tempo": 116.995, "speechiness": 0.035499, "acousticness": 0.011365, "danceability": 0.542202, "instrumentalness": 0.684925, "key": 0, "duration": 167.6795, "loudness": -6.352, "audio_md5": "", "valence": 0.381737, "mode": 0}}, {"song_hotttnesss": 0.0443, "title": "We Are Together (H.O.S.H. Remix)", "artist_discovery": 0.492388974476079, "artist_name": "Planet Of Sound", "song_type": ["remix", "studio", "electric"], "artist_hotttnesss": 0.514389, "artist_location": {"latitude": 51.5072648, "location": "London", "longitude": -0.1278328}, "song_currency": 2.0833333333333333e-05, "artist_familiarity": 0.333326, "artist_id": "ARVZXCI145701FAE8B", "id": "SOKDFJQ145B440F9BA", "audio_summary": {"time_signature": 4, "analysis_url": "http://echonest-analysis.s3.amazonaws.com/TR/ZL3HYwHGmfllDj3uGaK2xU3xLR0Zzikv9JCx0V6I-mTXzoQ-pH7zx2jcALKTnb52DE31PdSduaKyKJrDg%3D/3/full.json?AWSAccessKeyId=AKIAJRDFEY23UEVW42BQ&Expires=1445732751&Signature=6gG9/OD6gR/Bmf12jshwn9qr0/E%3D", "energy": 0.51924, "liveness": 0.034791, "tempo": 116.995, "speechiness": 0.100469, "acousticness": 0.011659, "danceability": 0.772547, "instrumentalness": 0.825783, "key": 3, "duration": 560.85333, "loudness": -11.947, "audio_md5": "", "valence": 0.415499, "mode": 1}}, {"song_hotttnesss": 0.0, "title": "We Are Together (Piemont Remix)", "artist_discovery": 0.492388974476079, "artist_name": "Planet Of Sound", "song_type": ["remix", "studio", "electric"], "artist_hotttnesss": 0.514389, "artist_location": {"latitude": 51.5072648, "location": "London", "longitude": -0.1278328}, "song_currency": 0.0, "artist_familiarity": 0.333326, "artist_id": "ARVZXCI145701FAE8B", "id": "SOEFWIJ145B4418426", "audio_summary": {"time_signature": 4, "analysis_url": "http://echonest-analysis.s3.amazonaws.com/TR/EEWmfQb7L88DCgL5VYCZAGTS24bVQpMrP2jOcdqN5sETB4HQf81mLlSCPTqPZaS7whZ7GvtAsVZLUn9rQ%3D/3/full.json?AWSAccessKeyId=AKIAJRDFEY23UEVW42BQ&Expires=1445732751&Signature=XIyPw%2BkpUbNWpYTZMkVMfNG/qQA%3D", "energy": 0.741984, "liveness": 0.049306, "tempo": 121.012, "speechiness": 0.055311, "acousticness": 0.003533, "danceability": 0.804843, "instrumentalness": 0.868964, "key": 3, "duration": 366.25333, "loudness": -6.852, "audio_md5": "", "valence": 0.764785, "mode": 0}}, {"song_hotttnesss": 0.0443, "title": "We Are Together [Mix Cut] - H.O.S.H. Remix", "artist_discovery": 0.492388974476079, "artist_name": "Planet Of Sound", "song_type": ["remix", "studio", "electric"], "artist_hotttnesss": 0.514389, "artist_location": {"latitude": 51.5072648, "location": "London", "longitude": -0.1278328}, "song_currency": 2.173913043478261e-05, "artist_familiarity": 0.333326, "artist_id": "ARVZXCI145701FAE8B", "id": "SOXRNIC14647A50635", "audio_summary": {"time_signature": 4, "analysis_url": "http://echonest-analysis.s3.amazonaws.com/TR/g9aMJwerRpBVoWahT8U9AFUJiof9k1vaOBA4qzMFmtJ4rLCLfRYe7EhJ1KC73a721XT-MUFnR4oW289iE%3D/3/full.json?AWSAccessKeyId=AKIAJRDFEY23UEVW42BQ&Expires=1445732751&Signature=vGeMiQFpASWHEeC9K6zlvLDtTgQ%3D", "energy": 0.739147, "liveness": 0.102575, "tempo": 116.992, "speechiness": 0.050471, "acousticness": 0.003746, "danceability": 0.743752, "instrumentalness": 0.804834, "key": 5, "duration": 229.75624, "loudness": -10.755, "audio_md5": "738d02175073249870b3b9d11c8efe3b", "valence": 0.351049, "mode": 0}}, {"song_hotttnesss": 0.0443, "title": "We Are Together (Piemont Radio Edit)", "artist_discovery": 0.492388974476079, "artist_name": "Planet Of Sound", "song_type": ["studio", "electric"], "artist_hotttnesss": 0.514389, "artist_location": {"latitude": 51.5072648, "location": "London", "longitude": -0.1278328}, "song_currency": 2.5e-05, "artist_familiarity": 0.333326, "artist_id": "ARVZXCI145701FAE8B", "id": "SOQVNKU145B4409E01", "audio_summary": {"time_signature": 4, "analysis_url": "http://echonest-analysis.s3.amazonaws.com/TR/8Oz8zQnfhbssa7YkUGC9qXlNgkv3cr5uhQ9zD5D7V9hfQifXJH4jo9VujRc_FzgoNjbVrC1D00aOQZs5M%3D/3/full.json?AWSAccessKeyId=AKIAJRDFEY23UEVW42BQ&Expires=1445732751&Signature=asISm95eqcSoc62CUOeD1oT58Zo%3D", "energy": 0.741806, "liveness": 0.148915, "tempo": 121.019, "speechiness": 0.062927, "acousticness": 0.008538, "danceability": 0.803849, "instrumentalness": 0.836289, "key": 3, "duration": 183.37288, "loudness": -6.44, "audio_md5": "d6dae076cfbfb8d4ef7dcf925bc14b59", "valence": 0.901285, "mode": 0}}, {"song_hotttnesss": 0.124365, "song_currency_rank": 1862035, "artist_discovery_rank": 14550, "title": "We Are Together (Jody Wisternoff Radio Edit)", "artist_discovery": 0.492388974476079, "song_hotttnesss_rank": 1326985, "artist_name": "Planet Of Sound", "song_type": ["studio", "electric"], "artist_hotttnesss": 0.514389, "artist_familiarity_rank": 99724, "artist_location": {"latitude": 51.5072648, "location": "London", "longitude": -0.1278328}, "song_currency": 0.00025714285714285715, "id": "SOSSCPS145B4409EBA", "artist_familiarity": 0.333326, "artist_id": "ARVZXCI145701FAE8B", "artist_hotttnesss_rank": 26844, "audio_summary": {"time_signature": 4, "analysis_url": "http://echonest-analysis.s3.amazonaws.com/TR/-kfmIQ2JSus60R5E2SrTN0PYkTmq4VtAhaeJfp6eqTeMNzpCStPhSW1EsCthIOaKGuT_ypX1u2hVzqAAY%3D/3/full.json?AWSAccessKeyId=AKIAJRDFEY23UEVW42BQ&Expires=1445732751&Signature=wjxuA9vfM8iAzlu5X8MRj//asp0%3D", "energy": 0.894137, "liveness": 0.496404, "tempo": 120.012, "speechiness": 0.037281, "acousticness": 3.2e-05, "danceability": 0.643985, "instrumentalness": 0.879145, "key": 8, "duration": 184.13288, "loudness": -8.242, "audio_md5": "3cca14128cdbaaa9a67c01130ea857af", "valence": 0.299884, "mode": 1}}, {"song_hotttnesss": 0.0443, "title": "We Are Together [Mix Cut] - H.O.S.H. Remix", "artist_discovery": 0.492388974476079, "artist_name": "Planet Of Sound", "song_type": ["remix", "studio", "electric"], "artist_hotttnesss": 0.514389, "artist_location": {"latitude": 51.5072648, "location": "London", "longitude": -0.1278328}, "song_currency": 2.173913043478261e-05, "artist_familiarity": 0.333326, "artist_id": "ARVZXCI145701FAE8B", "id": "SOPDKFD14692EAE005", "audio_summary": {"time_signature": 4, "analysis_url": "http://echonest-analysis.s3.amazonaws.com/TR/dE4OhgGT0aihQOpiE-WqhjwT_XUiTxMQV5Ozml-9R2OFhmB3KrowgJnzmxU4BTIRLi6uC1TLDSn0ZKcsU%3D/3/full.json?AWSAccessKeyId=AKIAJRDFEY23UEVW42BQ&Expires=1445732751&Signature=AN7yY0kSPf1iz5AfH1E1fHU0AuI%3D", "energy": 0.748813, "liveness": 0.139488, "tempo": 118.683, "speechiness": 0.046821, "acousticness": 0.006536, "danceability": 0.721728, "instrumentalness": 0.899089, "key": 0, "duration": 258.95288, "loudness": -11.136, "audio_md5": "98fe55625a10fb100577c242cb0418c5", "valence": 0.360664, "mode": 0}}, {"song_hotttnesss": 0.0443, "song_currency_rank": 5498776, "artist_discovery_rank": 14550, "title": "We Are Together (CJ Peeton Remix)", "artist_discovery": 0.492388974476079, "song_hotttnesss_rank": 3687122, "artist_name": "Planet Of Sound", "song_type": ["remix", "studio", "electric"], "artist_hotttnesss": 0.514389, "artist_familiarity_rank": 99724, "artist_location": {"latitude": 51.5072648, "location": "London", "longitude": -0.1278328}, "song_currency": 3.125e-05, "id": "SORWZOH14AD2469165", "artist_familiarity": 0.333326, "artist_id": "ARVZXCI145701FAE8B", "artist_hotttnesss_rank": 26844, "audio_summary": {"time_signature": 4, "analysis_url": "http://echonest-analysis.s3.amazonaws.com/TR/IBIgcARFS52CZnuyzvDwfj6helG3gMK9DLt4WqA3xBxPlPSTsXn-2KFfI80J8AmDdCPLwA9PQ0QTCZZb8%3D/3/full.json?AWSAccessKeyId=AKIAJRDFEY23UEVW42BQ&Expires=1445732751&Signature=zeFaq1reCt8LUDZUqeS5cX9xelI%3D", "energy": 0.599966, "liveness": 0.155221, "tempo": 120.945, "speechiness": 0.089836, "acousticness": 0.011264, "danceability": 0.53327, "instrumentalness": 0.776525, "key": 3, "duration": 388.76032, "loudness": -8.667, "audio_md5": "", "valence": 0.56618, "mode": 1}}, {"song_hotttnesss": 0.088599, "song_currency_rank": 4926025, "artist_discovery_rank": 14550, "title": "We Are Together (Jody Wisternoff Remix)", "artist_discovery": 0.492388974476079, "song_hotttnesss_rank": 2034672, "artist_name": "Planet Of Sound", "song_type": ["remix", "studio", "electric"], "artist_hotttnesss": 0.514389, "artist_familiarity_rank": 99724, "artist_location": {"latitude": 51.5072648, "location": "London", "longitude": -0.1278328}, "song_currency": 5.844155844155845e-05, "id": "SOBFZFB145773081F3", "artist_familiarity": 0.333326, "artist_id": "ARVZXCI145701FAE8B", "artist_hotttnesss_rank": 26844, "audio_summary": {"time_signature": 4, "analysis_url": "http://echonest-analysis.s3.amazonaws.com/TR/8dBUAQE3-X2U1hRCe7CIRmBhj0d3W6xA_v0mwPTFBAP-gCqDWefAdfWGPDdov6k8lRkS5_GhWb1hDTXgw%3D/3/full.json?AWSAccessKeyId=AKIAJRDFEY23UEVW42BQ&Expires=1445732751&Signature=hVafrafuLhNgdnfevk%2BVctgfjyo%3D", "energy": 0.831714, "liveness": 0.224835, "tempo": 119.993, "speechiness": 0.044684, "acousticness": 3.4e-05, "danceability": 0.664485, "instrumentalness": 0.858834, "key": 0, "duration": 465.162, "loudness": -8.715, "audio_md5": "7608cf4168d71584422398e68a72c04b", "valence": 0.391889, "mode": 0}}, {"song_hotttnesss": 0.088599, "title": "We Are Together (H.O.S.H. Radio Edit)", "artist_discovery": 0.492388974476079, "artist_name": "Planet Of Sound", "song_type": ["studio", "electric"], "artist_hotttnesss": 0.514389, "artist_location": {"latitude": 51.5072648, "location": "London", "longitude": -0.1278328}, "song_currency": 1.1111111111111112e-05, "artist_familiarity": 0.333326, "artist_id": "ARVZXCI145701FAE8B", "id": "SOATUMW145B443A8CD", "audio_summary": {"time_signature": 4, "analysis_url": "http://echonest-analysis.s3.amazonaws.com/TR/WdMIyQGqk0cdiNi4sElLhJh4ko6Sg8QvvNOqEHsbQd1HkkO4ccsvG9n4D7_Q5T3IaEuaYzSL2Lb8hsmfo%3D/3/full.json?AWSAccessKeyId=AKIAJRDFEY23UEVW42BQ&Expires=1445732751&Signature=Gw39dG0JtPjR2PwVIJ2ptvqedb0%3D", "energy": 0.668677, "liveness": 0.163915, "tempo": 116.998, "speechiness": 0.058779, "acousticness": 0.038596, "danceability": 0.719238, "instrumentalness": 0.826976, "key": 8, "duration": 240.5873, "loudness": -12.221, "audio_md5": "0112910901cf87f81b5011587a03e94f", "valence": 0.532564, "mode": 1}}, {"song_hotttnesss": 0.0, "title": "We Are Together (CJ Peeton Radio Edit)", "artist_discovery": 0.492388974476079, "artist_name": "Planet Of Sound", "song_type": ["studio", "electric"], "artist_hotttnesss": 0.514389, "artist_location": {"latitude": 51.5072648, "location": "London", "longitude": -0.1278328}, "song_currency": 0.0, "artist_familiarity": 0.333326, "artist_id": "ARVZXCI145701FAE8B", "id": "SOPTMRH14A4D79AB68", "audio_summary": {"time_signature": 4, "analysis_url": "http://echonest-analysis.s3.amazonaws.com/TR/4Wkv2A5L-Ndl5vdz-VdTCD-u9iCbsJeUxYSUk4GmIZhGA_qnreBsBAbbCUjP3UCYo2yh_fuIXLmqLoc5Y%3D/3/full.json?AWSAccessKeyId=AKIAJRDFEY23UEVW42BQ&Expires=1445732751&Signature=cN3scRqtTUbitnArDP23rfdPJhs%3D", "energy": 0.697801, "liveness": 0.364982, "tempo": 121.097, "speechiness": 0.081145, "acousticness": 0.065785, "danceability": 0.585752, "instrumentalness": 0.579482, "key": 0, "duration": 194.38018, "loudness": -8.757, "audio_md5": "", "valence": 0.17149, "mode": 0}}]}}