{"response": {"status": {"code": 0, "message": "Success", "version": "4.2"}, "songs": [{"song_hotttnesss": 0.459176, "song_currency_rank": 19234, "artist_discovery_rank": 201955, "title": "I Prefer Your Love", "artist_discovery": 0.3688288061017457, "song_hotttnesss_rank": 10586, "artist_name": "St. Vincent", "song_type": ["studio", "electric", "vocal"], "artist_hotttnesss": 0.633519, "artist_familiarity_rank": 625, "artist_location": {"latitude": 36.039147, "location": "Tulsa, OK", "longitude": -95.868667}, "song_currency": 0.03787856999050879, "id": "SOGEBCR1442E6E30ED", "artist_familiarity": 0.712521, "artist_id": "AR0JBXL1187FB52810", "artist_hotttnesss_rank": 3254, "audio_summary": {"time_signature": 4, "analysis_url": "http://echonest-analysis.s3.amazonaws.com/TR/3ggU0g3P-MTz2Cd1mgiPkwUY_apH-hsaVIItFINzftJ1XK_3z1slO8rtkz-lmw3KrLdt9PnlbDZC59pQ8%3D/3/full.json?AWSAccessKeyId=AKIAJRDFEY23UEVW42BQ&Expires=1445734992&Signature=rvOZas4PNp6NqiglSAVJeHJQJEY%3D", "energy": 0.631345, "liveness": 0.177141, "tempo": 127.054, "speechiness": 0.027773, "acousticness": 0.010001, "danceability": 0.60909, "instrumentalness": 0.11465, "key": 4, "duration": 216.13333, "loudness": -8.674, "audio_md5": "", "valence": 0.109251, "mode": 1}}]}}