{"response": {"status": {"code": 0, "message": "Success", "version": "4.2"}, "songs": [{"song_hotttnesss": 0.445064, "song_currency_rank": 39135, "artist_discovery_rank": 38183, "title": "Gush", "artist_discovery": 0.460612499995937, "song_hotttnesss_rank": 13821, "artist_name": "Pharrell Williams", "song_type": ["studio", "electric", "vocal"], "artist_hotttnesss": 0.908311, "artist_familiarity_rank": 212, "artist_location": {"latitude": 36.844004, "location": "Virginia Beach, Virginia", "longitude": -76.12036}, "song_currency": 0.01759229088019074, "id": "SOZVMCS14490C05E87", "artist_familiarity": 0.773245, "artist_id": "ARLIWDY1456895A560", "artist_hotttnesss_rank": 40, "audio_summary": {"time_signature": 4, "analysis_url": "http://echonest-analysis.s3.amazonaws.com/TR/0Ep8iAgfQ-DpIeMTB61hcqwgIXGbGnzrFKaltm29fyll2nk9JZrGm8WAsXmdCR4QvYLTcBM3zUtYruKKU%3D/3/full.json?AWSAccessKeyId=AKIAJRDFEY23UEVW42BQ&Expires=1445733969&Signature=S6ZWCa6Me7cEW04yren7dylt5rU%3D", "energy": 0.696542, "liveness": 0.052311, "tempo": 111.999, "speechiness": 0.053684, "acousticness": 0.111643, "danceability": 0.796312, "instrumentalness": 1.5e-05, "key": 4, "duration": 234.66667, "loudness": -7.062, "audio_md5": "", "valence": 0.73134, "mode": 0}}]}}